{"statistics":{"identical":210,"minorChanges":1,"relatedMeaning":3},"text":{"comparison":{"identical":{"source":{"chars":{"starts":[31,225339,279318,280618,280793,280866,281164,281998,285140,285210,285225],"lengths":[76,39,76,105,67,36,748,64,56,8,391]},"words":{"starts":[2,33466,40862,41029,41050,41059,41094,41187,41550,41562,41565],"lengths":[10,6,7,12,7,3,84,8,9,1,52]}},"suspected":{"chars":{"starts":[47,59071,77449,77849,77983,78051,78092,78843,79887,79953,79968],"lengths":[76,39,76,105,67,36,743,64,56,8,391]},"words":{"starts":[3,9220,11736,11789,11805,11813,11818,11903,12024,12036,12039],"lengths":[10,6,7,12,7,3,84,8,9,1,52]}}},"minorChanges":{"source":{"chars":{"starts":[285197],"lengths":[2]},"words":{"starts":[41560],"lengths":[0]}},"suspected":{"chars":{"starts":[79944],"lengths":[2]},"words":{"starts":[12034],"lengths":[0]}}},"relatedMeaning":{"source":{"chars":{"starts":[281157,285200,285219],"lengths":[6,9,5]},"words":{"starts":[41093,41561,41564],"lengths":[0,0,0]}},"suspected":{"chars":{"starts":[78088,79947,79962],"lengths":[3,5,5]},"words":{"starts":[11817,12035,12038],"lengths":[0,0,0]}}}},"value":" \n \n   \n  \n \n ######## ########## ###########  From Wikipedia, the free encyclopedia\n \n \n Jump to navigation Jump to search   ##### ######### ####. ### ##### ######## ###### ###, ### ### ################.\n  \n ##### ######## ############ ###### ######\n  \n  ######## ########## ########### #####   ####### ######, ########### ## ########\n #### ### ########    ##### ##########   ####### ######, ##### ## ##### ################\n### ####,\n### #### ####, ### ####, ###### #########    ######### ###### #######   ############ #### ######   ##. ## ##### ##   ######### ###### ###### ### ######\n###### ## #####   ############ ### #### ####   #########  #### ######## ##########   #### ######\n###########  ###### ##### ########\n#### ######   #### ######  ###### ####### ### #######   ## ##########  ###### #######   ###/#### \n ### ##\n ###\n  ####### \n  ### ## ######\n  ###/#### \n  #########/######### ### \n     ######## ####### ###.###    ### ######## ########## ########### ##### ## # ##### ############ ########## ###### ## ##### ######## ######## ## ## ##### ### ## ### ###### ###### ### # ## #######. ## ## ###### ########## ## ## ### ####### ##### ############ ########## ###### ## ### #####. ### ### ## ## ###### ###### ## ### ########## ######,### ##### ## ########## ## #### ##### ##### ## ### ############# ########## ########### ## ### ######## ######### #### ### ########## ## ### ###### ######. ### ### ## ### ## ### #### ##### ############ ###### ####### ## ### ###### ###### ### ######. ### ####### ### ### ####### #### #### ######## ## ####### ###### ###### ### ######.###### \n ### ###### ### ####### ## ### #### #### ## #### #, ####, ## ### ########## ########### ## ####### #####.###### ### ###### ####### ### #### ######## ########## ########### ## ###### #, ####, ##### ####### #### ### ######### ######## ########## ###### #####. ### ######## ####### ############# ## #### ## ########## #### ####### ### ######## ### ## ### #### ####### ####### ## ### ####### ##### ## ### ##### ###### ## ####### #########. ### ############# ### ### ## ####### ### ######## ### ## ####### ####### ## ########, ### ######. \n   ########  \n   # #######  #.# ######## ### ####### ###### ###########\n #.# ######## #########, ###### ######### ### ########### ###########\n #.# ####### ########## ###########\n #.# ####### ### ###### ######### ###########\n #.# ###### ### ##############\n #.# ############# #########\n #.# ##### ############\n  \n # #####\n # ####### ######\n # ########\n # #############\n # ##### ########\n # ############# ############\n  # ###### ###### ### ########## ############  #.# ########## ############\n  \n  # ####### ######  #.# ########## ### #############\n #.# #######\n  #.# ####### #######  #.#.# ############# #########\n  \n #.# #######\n  \n ## ### ####\n ## ##########\n ## ####### #######\n ## ######## #####\n  \n #######  ######## ### ####### ###### ###########  #### ######## ########## ########### ## ####### \n ### ########## ########### ## ####### ### ####### ## #### ## ###### ## ### ##### ### ###### ###### ## ### ############ ### ########## ###### ###### ### ######. ## ######## #, ####, ## #######, #######, ######, ### ####### ####### ###### ### ### #### ############## ## ##### #### #######, ## # #### ### ### ### ###### ## ## ### ##### #### ###### ## ### #######.### ### ##### ###### ### #### ## ##### ######### ## ### ##############. ######## ##### ### #### ####### ######## ## ############ ########## #######, ######### ### ######## ########## ###### ### ### ###, ### ### ### ### ##### ###### ## ####### ## #### ######### ## ##### ###### ## ##### ######. ###### ### ##### #####, ### ####### ## #### ## ### ### ### ### ############# ###### #### ## ######### ####### ## ##### ####### ########### ##### #### ## ### ###### #############. ### ########, ### #### ### ######## ######### ####### ##### ## ### ### ### ### #### ######## #### #####, ### ### #### ### ######## ########### ###### ### ### #### ### #####. ##### ## ### ####### ######, #######, ### ##### #### #### #####, ############, ###########, ### ######### ###### ## ### ###, ##### ########### ### ### ## ### ###### ## ###### ### ########## ####### ## #### ############.### \n ## ###### #, ####, ### ######### ### ##############, ########, ##########, #########, ######, ### ############### #### ### ###. ## ######### ## ### ###### ### ## ##### ######## ##### #############, ### ###### #### ### ####### ## ### ####### ######## ########## ###########, #### ###### ### ###### ###### ######## ### ##### ######### ####, ######### ########.### ## #### ###, ### ### ###### ### ##### ####### ## ### ###. ## ### ####### ### ####### ## ### ### ##### ## ## #########, ### # ######, ### #### ### ######### ### ####### ### ##########. \n ### ### ###### ### ######### ########## ####### ## # ### ## ##### ### ##### ######,### ## #### ## ##### ###### ### ####### ########## ### ########. ## ####, ### ### ############ ## ###### ##########, # ####### #### ######### ##### #######, #### ### ###### ####### ### ######## #### ## ##### ########### ### ### #### ######, ###### #######, ############ ########, ########### ######, ######### ######, #### ##### #######, ########## ##########, ### ######## #########, ### ## ##### ###### ## ### ###### #####. ### ####### ## ########### ### ### ######## ############ ########## #### ## ###### ######. ### ##### ####### #### ### ########## ## ######### ## ####, ### #### ## ##. ##### ## ####. ### ######### ###### ##### #### #########, ### ####, ## ########## ## #### ### ### ####### ######### #### #### #####, #######, ## ####### ## ####. \n ################# ###### ###### ##### ### ### ##### ####### ## ### ####### ###### #### ## ###### ### ### ### #### ######. ## ######## ### #### ######### ###### ## ###### ####### ##### ## ### ##### ################, ###### ######, ####### #### ### ########## ######## ## ####.####### ###### ### ### #### ### #### ###### ######## ####,####### ### ####### ################ ####### ### #### ## ### ###### ##### #### ####, ######### ##### ###### #### ### #######, ######### ############ ####### #### ### ######, ### #### ##### #### ### ########## ########. ###### #### ######, ### ########### ######, ### ## ###### ###### #####, ### #### ### ############# ### ########### ########## ## ### ######## ##### #######.#### ## ######### ######## ### ########## ########, ### ###### ########## ### ######### #### ##### ## ####.#### ## # #### #### ### ####### ## ##### # ##### #### ### ### #### ##### ## #### ####### #### ### #### ###### ## ####### ## ######### ### ####, #### ## ####### ### ### #### ##### ## ### ########. \n  ######## #########, ###### ######### ### ########### ###########  ## ####, ###### ###### #### ####### ###### ### ###### #######, ##### ####### ######## ##### ### ##### ### ##### ### ########, ### #### ## ## #### ### #### ## ###### ### ###### ## ######## #######. ###### #### ########### ####### ### ###### #### ### ######## ## #### ### ###### # ######## ########## #### ## ### #####, ####### ### ###### #### ####### ## ####### ##### ### ########## ####. ######### ####### #### ########### ###### ### ## ### ######## ######### ## ### ####### ## ######## #### ######. \n    \n #### ####### ######### ####### #### ########### ## ####.\n \n\n ### ##### #### ######### ## ### #######. ### ## #######, ### ##### ### ##### ### ########, ###### ### ##### ######## ############# ## ### ### #### #### ## ####. #### ############ ###### ## ### ####### ## ### #######. #### ### ### ### ### ##### ## #######, ### ######## ## ## ### ####### ###### ### ######## ## ####. ### ########## ####### #### ## ### ### ############ ####### ## ### #####.#### \n ####### #### ######, ### ### ######### ## ###### #### ### ##### ## ### ########### ###### ## ### #######, ### ############ ######## ## ### #########, ### ######## ######### ## ############ ## ###### ### ############ #####, ### ### ##. ##### ##### ###### ## #######, ## #### ## ### ######## ## ### ##### ######### ##########. ### ####### ####### #### ########## ######## ###### ### ##### ### #### ## ####. #### #### ## ####, ### ###### ######## #### # ## ## #####, ########### ### ####### #####, ####### ########### #### ######## #### ########, ### ##### ####### #### ######### ## ####### #### ##### ######, ######### #####, ### ####### ####. \n ## ####, ### ###### ##### # ### ######## ###### #### ### ######### ## ### ######## ########## ########### #####. ### ####### ####### ## # ####### ###. ### ### ###### ### #### ######### ####### #### ## ### ###, ###### ############ ##### ##### ## ### #########. #######, ### ##### ####### ######, #### #####, ###### ## ### ###, ## ### #### ####### ############# #######, #### #####, #### #####, ### ### ######.#### \n ## ####, #### ######, ### ####### ### ###### ## ##### ###### ##### ###### ######## #### # #### #####, ####### ### ###### ### #### ######## ## ### #####. ## ############ ### ########## ## ### ######### ##### #### ##### ## # ##### ## ### #######, ######## ### ######### ###### # ########## ###### ## ##### ### ######### #######, ######### ## ######, ##### #### ## ################ ## ###### #### ############# ##. #### ###### #### # ##########, ####### ###### ### ##### ##### ## ##### ######## ### ##### ######### ####### #### #### ##### ########### #### ## ######## ## #### ### ######.# ### ###### #### ####### ## #### ##### # ##### ###### ## ### ######## ## ### ### ######## ## ##### ### ##### ###### # ####### ## ### ### #####.######## \n ### ### ######### ## ####### # ###### ## ##### ##### ## ### #####, ######### ###### ###### ## ### ######## #######, ## #### ####### ## ####### ##### ## #### ####### ##############. ### ### ######## ####### ###### #### ######, ### ####### ##### ## ### ## ### #### ###### ######. #### #### ## ####, ### ### #### #### #### ########## ## ##. ## ####, ### ######## ##### #######, ######### #########, ### ####### ###### #### ### ### ####### ######### ### #### ##### ###### ######### ### ###### ## ##.#### ### ### ####### #### #### ## ##### #### ###### ## #### ######## ### ##### ## ##. ######### ### #### ######, ### ####### ####### # ########## #### ######## ### ### ######## ## #### ### ########## ## ### ###, ####### ### ###### ## ########## ## ### ###### ## #### #### ## ##. ### ########## ##### #### ### ### ####### #####, ###### #######, ####### ######, ### ### #### #### #### ### ######## #####. #### ## ### ####### ##### ## #### ### #### ###### ############, #### #####, #### ######, ###### ######, ##### #####, #### #######, ##### ######, ##### #######, ###### ######, ### #####, ### #### ########. ### ### ## ### ######, #######, ### ######### ## #######, ### ########## ### ############ ###### ###### # #### ######### ### #### # #### ########## ## ###### ### ######. \n  ####### ########## ###########  ### ###### ##### ### ##### ########### ##### #### ######### ## ####.#### #### #### ####, ####### ##### #### ### ##### ####### ###### ### ###### ####### ### ### ####### ###### ############, ########## # ###### ## ########### ###### ## ### ######## ## ### ###.#### ### ### ### ##### #### ##### ## ### #### #### ######## # ########## ############ ####, ### #### ##### ###### ####### #### ##### ## ##### ### ###### #####, ####, ### #####.#### ## ### ## ####### ## ### #####, ####### ### ### ###### ## #### ########## ##### #### ### ### ####### ## ##### ######.#### #### ## ### ##### #####, ### ### ##### ### #### ######### #########, ### ###### #########,#### ######## ### ##### ## ## #####. ##### ##, ##### #### ### ### ##### ##### ########### ######## ########.#### ## ######## #, #### ##### ##### ###### ############ ## ### ###.#### ##### ### #### ########## ## ####### # ##### #### ## ### ###### ## ### ###### ###### ### ######.######## \n    \n ####### ###### ##### ## ### # #### \n \n\n ####### ###### ####### ### ###### ## #### #### ### ####### #####, ######## #### ######## ## ### ######.#### ## #### ### ####, #### ###### ### ##### ###### ## ### ######### #######, ##### ####, ####### #####, ### ######### ############ #### ##### ### ######, ######## ### ##### ## ## #####.#### ### ####### ####### ### ### ############ ### ############# ## #### ### ####, ### ## ##### ##### #### ### ##### ##### ######.#### ###### ### ####### ###### ### ### ##### ## ### ########### ## ##### ##### ###### ### ####### #######.######## ###### ######## ### ############ ###### #### ### ####### ####### ## #### ### ####.#### \n ### #### ####### ########## ##### ####, ### ##### ## ### ####### ### #####, ######## ####### ###### ## ### ######, ##### #### ####, #######, ##### ########, ####### #####, ####### ######, ##### #######, #### ######, #### ########, ##### ######, ####### #######, ### #### #### ####### ######### ########.#### ### #### ### ####### ## ### ######## ######## ########## #### ## ####,#### ### ## ####### #### ### ##### ####### #### #### ####### ## ### #### ## #### ## ###########.######### ####### \n ## ####, ### ### ######## ## ###### #### ### ######## ## ### ######### ######### ### ### ####### #######.######## ## ####, ### ### ####### # ####### ######, ### ####### ######## ########## ########### ######.#### \n ## ####, ### ### ###### ##### # ####### #### ######### ### ###### ######## ##### # ### ##### ######### ##### ## #######.#### ## ### #### ### ####### ### ####### ##### #### ####, #### ### ###### ### ####.######## ## ####, ### ### ####### ##### ###### ### ##### ###### ### #### ## ### ### ### ############. ## ### ### ###### ##### ############ ###.#### \n  ####### ### ###### ######### ###########  ##### ### ####### ## ### ####### ##### ############ ###### ## ### ###### ## ####, ### ####### ########## ### #########. ### ### ####### ###### ## ##### #### ####### ### ### ### ####### ##### ## ##### ######## ######## ## #### ## ###### ## ## #######, #### ## ######. ### ###### ### ##### ######## ### ### #### ############ #### ### #####, ### ######### ###### ### #### ###### ####### ### ##### #### ##### ########### ############# ### ### ######. ### ##### ######### ### ##### ## #### ####### ### ####. ## ####, ### ###### ######## ## ### ######, #### ## #### ## #### ##### ## ### ####### #######. \n ### ######## ##### ### ###### ## # ####### ######## ####### ####### ### #### ## # ######## #### #### ####### ### ####### ###### ### ####### #######. ## ########, ####### #### ######### ### # ##### ## ### ##### #### ### ####### ##### #### ## ######, ### ### ###### ######### ######## ### ####### ### #### ## #######. \n    \n #### ###### ######### ###### ##### ## # ######## #### #### ####### ### ### ####### ###### ### ### ######### ######### \n \n\n ##### ### ##### #### #### ### ##### ####### ############ ###### ## ####, ### #### ###### ######## ### ########## ###### ##### ######### ###### ###########. ### ##### ####, ### ## ##### #### ######## #####, ###### ####, ### ######### ######, ### ### #### ###### #### ### ###### ###### ###### ####, ### ### ###### #### ### ###### ######### ## ### ##### ###### ### ##### ### #####. ### ######/##### ######### ######### ## #### #### # ######### ##### ## ### ##### #### ### ######### #########, ### #### ### ## ###### #####. ### #### ###### ### # ####### ## ### ######## ####### ####### #######, ### ###### ####### ### ### ####### ######, #### ### ####### #######, ### ##### #### ############, ###### ## ##### ### ### ##### ## #### ######, ### #####, ### ##### #######. \n ## ####, #### ###### ### ### ###### ######## ## ### ######, #### #### ######### ### ###### ########## ####### #####. ###### ### ### ##### #### ####### ### ###### #### ######## ###### ##### ## ### #### ###### ##### ####### ### ###### ## ##### ##### ### ############ ##### ### ######### ## ######### ######.#### \n ### #### ### ######## #### ### #### ## ####### ####### ## ##### ## ### ####### ##### ####, ###,###.#### ## ### ### ## #### ######, ### ####### ### ### ###### ####### ##### ####### #### #### #### #### ### ##### ## ### ### ###### ### # ###### #### ####. ### ###### ### ### ##### ## ####### #### #, #####.#### ###### ### ##### ## ### ####### ###### ### ### ### ## ######## ###### #### ### ## ### #### ########### #### ##### ####### ## ### ####. ### #### ###### ######, ### ### ########, #### ### ##### ####, ####### ## # ###### #### ### ####### ######## ## ##### ######## ####### ## ####### ## ###### #### ### ############. ### ####, ### ## ###### #####, ###### ####, ### ##### ####, ### ## #### #### ### ###### ####### ### ###### #########, ## # ####### ### ### ########## ## ### #### ######. ### #########, ### ## #### ######## #### ######## ### ###### ####, #### ### ###### ## ### #####. #### ### ### ########## ##### #####. ######## ##### ######, ##### ####, ##### #####, ### #### ########## ########## ##### ##### ### ############. \n ## #### #, ####, ## ##### ##, ### ### ######### ####### #######.#### ##### ### ##### ### ##### ## ### ###### #### ########, ### ####### ### ###### ######## # ### ########## ########## ######### ## ######## #, ####, ####### ## # ######### ####### ######.#### ######### ### ######### ######, ### ##### #### #### # ###### ## ### ###### #### ### #### ## ###### ####, ###### #####, ### ##### #### ####### ######## #### ######### ##### ######, ####### #########, ### ##### ######. ### #### #### ## ## ###### ### ####### ## #### #####, ######### ##### ###### ### ##### ## ### #####. ##### ####### ##### ######## #### ### ######### ######, ##### ######### #### ##### ####### #### ### ### ####### ##### ## ### #### ### ######. ### ### ##### ##### #### ### # ####### ## ### ######### ###### ######, ##### ### ##### ######## ### #### ## #### #####. ### ### #####, ############ ##### ##### ####### ## ######## #, ####, ####### ## ##### ## ### ### #### ###### ######. ## ### ######### ## ### ######, #### ######. \n  ###### ### ##############  ######### ### #### ######, ###### ##### ######### #### ## ##### ###### ## ### ######### #########. ##### ### ### ######### ## ##### ###### ###### ##########, ##### #### #### ## ### ###### ##### ######## ## ### #####. ### ######### ####, ## # #######, ### #### ### ###### ######### #### ### ######### ######### ### ######## ## ##### ##### ## ### ##### ##### ### ############. ### ######### ## ##### ### ##### ######### ## ####, #### ### ########, ###### ###### ##### ###### ## # #### #####, #### ### ##### ######## ###### ####### ####### ### ### ##### ## #### #####, #### ###### ##### ###### ###, ### ##### ## #### #### #### #### ## # ###### ######## ###### #######. \n ###### #### ###### ## ####, ###### ##### ###### #### ### ######. \n ############# ######### ####### ############ #### ## ####### ### ####### \n ######### ######## #### ##### ##### ######## ### ###### ######## ######### ### ###### ### ### ## ### #### #####, ## ########## ###### ## ############# ####### #### ##### ######## #### ####### ######### ## ### ##### ## ######## ## ### ###. ##### ####, ### ### ### ##### ########## ##### ## ########## ####### ## ### ### ###### #### ####, ### ##### ####, ## ### ########## ######## ####. ### ####### ###### ###### #### # ###### ## ############# ####### ## ### ####### ##### #######, ############ ## ######### ### ########## #### ### ## ### ######.#### ### ######### ## ### ####### ###### ### # ###### ### ############# ####### ############ ## ######### ######### ####### # ########### ##### ## ## ##### ### ############# ####### ### #### #### ###### ## ##### ### ############# ######.#### ## ####, ### ####### #### ##### ####### ##### #### ######## ## ##### ### #### #####, ######### ######## ####### ##### ### ######, ###### ######## ### ##### ######## ##### ## ###### # #### ##### ### # #### ## ### ###. \n ##### ############ ## ####, ## ########## ##### ######, ### ######## ########## ########### ######, ### ###### ### ### # ######, ### #######.#### ###### ### ###### ### #######, ##### #### ###### ###### #### ### ### ##### ######## ### ########### ########## ###########, ### #### ## ### ############# ######. \n ### ##### ##### ### ######## ########## ## ### #######, ### ### ######## ## ##### ########, ## ### ######### ####### #### ###### ## ## ######### #### ## ####. \n ### ####### ########### ######### ## ######## #### ## #### ### ### ####### ####### ## ###### ###### ## ######### #######. ### #### ######## ## ### ####### ## ####. \n # ### ######## #### #### ### ########## ## #### ##, ####, ### ### ####### ######, ####### ### ##### ###### ## ### #### ## #### ## ##### ### #### ### ###### #### ## ## #######.#### ############ ## ########, ### ### #### ######## # ### ###### ### ### ######### ######## #### ######## ####### ####### # ###### ####, ####, ### ########### #### ### ######## ####. #######, #### ####### #### ##### ## ##### ####### ### ### ### ####, ###### #### ## ### ### ###### #### ###, ### ### ######## #### ###. \n ############ ##### ######### ## ######## ##, ####, #### ######### ####### #, ####, ### ### ##### ###### ## ### ########### ####### ########## ## ### ##### ## ### ####### ######. ### ###### ### ########## ## ######## ###### ########## ### ######### #### ######## ###### ###### ## ### ########## ####.#### ### ######## ########### ### ##### # #### ## ###### ## ### ####### ####### ### ### #### ### ### ####.#### ## ## ### ####### ######, ### ### #### ####### ### ############ ## ####, ######### ### ######## ########, ######. ### ##### #### #### ####### #### ### #### #### ###### ### ######### #######, ##### ####### #### ####### #### ### ####### #### ########## #### ######## #### ######## ####### ######, ### #### ### #######.#### \n ### ####### ###### ## ############# ##### ##### ## ############# ## #### ##, ####, #### ########### #### ####### ### ####### ### ####### ### ## ########## ##### ## ########## #### ### #### ### ####### ### #### ## #### ##### ######### ### ##### ###### ## ##### #####.#### ## ###### ##, ####, ####### ####### ###### ## ### ####### ####### ####### ## ### #############. ####### ####### ## #### #### ####### ######## #### ######## #### ####### ### ######## #### ### ### ###, ### ## ####### #### ######## ########## ### ####### ## ####### ####### ### ###### ##### ## #### ### ####. ### ############ ##### ##### ###### ### ########### ### #### ####### ### # ######### ##### ### # ########, ########### ########.#### ####### ###### ## ###### ## ###### ### ### ######## ## ######## ####.#### ######### ## ## ########### ##### ## ###### ##### ## #### # ## ### #### ####### ########## ###### ####### ### ### ####### ###### ### ########## #####, ######## ### #### ######### ### ####### ####### ## ####### ####### #### ##### ###### ### ####, ##### ### ## ######### ## ### ### ####. ## ####### ##### ########## ###### #### # ## ### #### ###### ####### #######, ##### #######, ###### #### #### ## ## ###### #### ######### ######### ### ########## ### ######### #######.# #### \n ### ### ##### ## ######### ######## ### ####### ## ### ####### ########### ## ######## ## ######## #### ## ##### ##, ####.#### ### ####, #######, ##### ### #### ##### ## ### ####### # ####### ##### ## ### #### ## #######, ##### ### ######## ## #### ### ########### ## ####### ### ### ######### ### ####### ## ### ###### ##### ## ########. ######### # ##### ####, ### #### ## ####### ####### #### ### ######### ##### ## ### ########### ## #### #, ####, ######## ### #### ## #### ## ######## #### ########### ## ######## ### ########### ### ##### ### ####### ## ### ###### ##### ## ########.#### ### ######## #### ####### ##### ####### ## ### ####### ######. \n ### ##### ####### #### ## ### ###### ### ## ### ###### ### ###### ## ### ###### ##### ###### ###### ## ####### ##, ####, ####### ### ####### #### ### ### ###### #######.#### \n # ####### ####### ##### ## ######### #, ####, #### ### ######## ####### ### ### ### ### ######## #######. ### ##### ######### ##### #### ###### ## ####### #, ####, ### ########### ######## #### ### #### ### ### ########### ###### #### ####, ### ##### #### ########### ######## ### #### #### ##### ### ######### ## ### ####### ######. ### ### ### ### ####### ######## ####### # #### ## ####### ##, ####.######## \n ### ##### ######## ### ###### ##### ## ######## ###### #### ##### ## ####. ## ### ########, ### ### ###### #### ##### ### ####### ####### ## ### ## ##### ## ###### ## ##### ## #### ##,### ####. \n ### ####### ### ######, ######### ## ##### ######## #, ####, #### # ####### ####### ### ######### ######## ###### ######### ### ### ####### #####, ### ######### ### ## # ##### #######. ### ####### ########## ##### ## ######## #, ####, #### ####### ### ###### ######## # ### ########## ########## #########, ### ### ###### ##### ## ######### ###. \n ##### ### ####### ######, ### ### ####### ####### ####### ########## ### ########.#### ###### ### ####### ######, ##### ####### ## ############ ##### ## #####, ### ###### ############ #### ###### ######## ## ### ######## ## ############. ###### #### ######## ########, ### ####### ########## ######### ### ####### ####, ### ## ######### #### ### ###### ### ### ########, #### ######## #### ######### ## ### #######, #######, ### ########## #### ### ######### #### ## #########. ## # ######, ### ####### ### ### ########## ########## ## #### #### ####### ## ####, ######### ########## ## ####, ### ####### ## #### ## ### #######, ##### ### ######## ### ########## ####### ## # #### ######### ####.#### ##### ## ######## ####### ## ### ############ ####### ### ######### ###### ### ######### ###### ## ### ###.# \n ###### ########, ### ### ########## ## ### ### ####### ########, ######## # ######## ### #### ### ### ## ##### ##, ####, ##### ###### ####### ## #### ###### ######. ######## ### #### ##### ####.# #######, ### ####### ####### ##### ### ### ############.#### \n ##### ###### ### ##### ## ### ### ####### ##### ## ###### #, ####, ## ## ######### #####, ######## ### ###### ###### ##### ## ### ####### ### ### ##### ######### #####.######## #### #### ##### ### ### ##### ######### ###### ##### ## ### ## ### #### ##### ############ ###### ## ##### #######.#### \n ### ### ######### ## ##### ##, ####, #### ## ##### ##### ### ## ## ### ###### ##### ## #### ######### ####### ############# ####### ## ######## #### ########, ######### #### ### ####### ######. ### ########### ############# ####### ##### ###### ## ### #### ##### ## #######, ######## ###### ####, ####### ### ##### #### # ############## #### ##### ###### ## ### #######, ### ##### ####### ############# #.# ## #.# ######. ### ### ##### ###### ### ##### ##### ##### ######## ############ ###### ###### ## ##### ######### ########### ##### ## ######## #### ########, ### ### #### ## #### # ####### ############ #### ###### ## ### #### ########.#### ### ##### #### ## ######## # ###### ########### ### ### ############ #####, ### ###### ## # #### #### #######.#### \n ## #### #, ####, ### ### ######## ## ####### ######### ## ### ##### ## ## ####### ######### ## ### ######## ######, ###### #### ####### ########## ### # ######## ##### ######. ### ###### ##### ## ##### ## ### ####### #### ###### ### ########## ###### ### #### ### ###### ######, ### ## #### ### ########### ## #### ## ######### ## ######## ### ## #### ####.#### \n ### ### #### ########## ######## ### #### ######## ### ### ## ##### ######### #### ### ####### ######. ### ###### ########## ###### ### ###### ####### ############. #######, #### #### ##### #### #### ## ### ######### ### ############# #######, ##### ## ### ###### ########### ##### #######, ### ###### #######, ##### ## ### ###### ####### ##### #######, ### ### ##### ####### ########, ## ## ######## ## # ##### ####.#### \n ##### ### ##### #### ## ####### ######## ########## ########### #####, #### ## ######### ######## ########## ########### #####, ######## ## ### ######## ########## ###########, ### ######### ## ######## ########## ########### \n   #######\n #######\n ######\n ####\n #####\n #####\n #########\n #######\n ######\n #####\n #####\n #######\n ####\n #####\n #######\n #########\n #######\n #########\n ########\n #####\n #######\n ############\n ##### #######\n #######\n ####\n ########\n #####\n ####\n ########\n ######\n \n     ### ### ########### ###### ##############     ######## ########### ### #########     ### ### ########## ## #### #### ## #####, ### ####### # ######## ## #### ##########, ##########, ### ########### ######### ######## ## ## #####. ### ###### ###### ## #### ## ## ##### ### ### ## ####### ## ######. \n ### ####### ###### ############ ####### ###### ##### #### ### ########### ## ##### ######### #### #### ##### ####. ### ####### ########## ######### ### ########## ## ### ####### ######. ########## ### ########## ############ ## ### ###### ###### ### ###### ## # #####, #### ##### ### ## ### ####### #### ## ### ######## ######## ##### ### ## ### ####### #### ####, #### ## ### #######, ##### ## ### ########, ### #### ## ### #######. \n    ########  ####  ####/#####  #####  ########  ###########  #######  ######     ####### ##########     ########   ###### #######   ######, #############   ## ######  ##,###   ########## ########### / ###.######## ##.######### / ##.####### ###.####### ####### ########  ####     ######## ####   ### #### ####, ### ####   ######## ######  ##,###   ########## ########### / ###.####### ##.######### / ##.###### ###.####### ######### #####  #####  ####     ### #### ######   ### #### ####, ### ####   ####### ###### ######  ##,###   ########## ########### / ###.######## ##.######### / ##.####### ###.####### #### #### #######  ####     ############ #####   ############, ############   ##### ##### ######  ##,###   ########## ########### / ###.######## ##.######### / ##.####### ###.####### ############# ######  #####  ####     ####### #######   #######, #######   ########## #####  ##,###   ########## ########### / ###.######## ##.######### / ##.####### ###.####### ######## ########  ####     #######   ####### #####   #######, ########   ###### ######  ##,###   ########## ########### / ###.######## ##.######### / ##.####### ###.####### ######## ######  ####     ######### #########   #########, ####   ###### ######## ##########  ##,###   ########## ########### / ###.######## ##.######### / ##.####### ###.####### ########## ##########  ####     ####### #######   #######, ########   ###### ####### #####  ##,###   ########## ########### / ###.######## ##.######### / ##.####### ###.####### ######## ########  #####  ####     ####### ######   ############, #######   ####### #### ##########  ##,###   ########## ########### / ###.######## ##.######### / ##.####### ###.####### ######## #######  ####  ####     ######### #####   #########, #########   ###### #####  ##,###   ########## ########### / ###.######## ##.######### / ##.####### ###.####### ########## ######  ####     #########   ####### #####   #######, #######   ##### #### #####  ##,###   ########## ########### / ###.######## ##.######### / ##.####### ###.####### ######## ######  #####  ####     ######### #######   #########, ##### ########   ######## ######  ##,###   ########## ########### / ###.##### ##.######### / ##.#### ###.####### ########## ########  #####     ##### ####   #####, #######   ######## ######## #####  ##,###   ########## ########### / ###.######## ##.######### / ##.####### ###.####### ###### #####  ####     ####### #####   #######, #######   ##### ######  ##,###   ########## ########### / ###.######## ##.######### / ##.####### ###.####### ######## ######  ####     ########## #######   ##########, #.#.   ####### ### #####  ##,###   ########## ########### / ###.######## ##.######### / ##.####### ###.####### ########### ########  #####     ####### ##########     #########   ###### #######   ######, ########   ##### ######  ##,###   ########## ############ / ###.######## ###.####### / ##.####### ####.##### ####### ########  ####  ####     ######### ############   ###########, #########   ###### ######  ##,###   ########## ########### / ###.######## ##.######### / ##.####### ###.####### ########## #############  ####     ######## #### #######   ######## ####, ########   ########## ###### #####  ##,###   ########## ########### / ###.######## ##.###### / ##.####### ###.#### ######### #### ########  #####     ######## ##### #######   ########, ######   #### ######  ##,###   ########## ############ / ###.######## ###.######### / ##.####### ####.####### ######### ##### ########  ####     #### ####   #### #### ####, ####   ###### ##### #### #####  ##,###   ########## ############ / ###.######## ###.######### / ##.####### ####.####### ##### #####  #####     #######   ###### ##### ########   #######, ##########   ###### #####  ##,###   ########## ############ / ###.######## ###.######### / ##.####### ####.####### ####### ##### #########  #####     ### ####### ########   ### #######, ##########   ####### ######  ##,###   ########## ############ / ###.######## ###.######### / ##.####### ####.####### #### ####### #########  #####     ### ####### ######   ### #######, ##########   ####### ######  ##,###   ########## ############ / ###.######## ###.######### / ##.####### ####.####### #### ####### #######  #####  ####     ####### ####   #######, #######   ####### ##### ###### #####  ##,###   ########## ############ / ###.######## ###.######### / ##.####### ####.####### ######## #####  ####     ########## #####   ##########, ##########   ###### # ######  ##,###   ########## ############ / ###.######## ###.######### / ##.####### ####.####### ########### ######  #####  ####     #########   ###### #########   ######, #####   ######## ######## ######  ##,###   ########## ########### / ###.######## ##.######### / ##.####### ###.####### ####### ##########  ####     ####### #######   #######, #####   ###### ######  ##,###   ########## ########### / ###.######## ##.######### / ##.####### ###.####### ######## ########  #####     ####### #########   #######, #########   ##########  ##,###   ########## ########### / ###.######## ##.######### / ##.####### ###.####### ######## ##########  #####     ### ####### ########   ### #######, #########   ######## #### ######  ##,###   ########## ########### / ###.######## ##.######### / ##.####### ###.####### #### ####### #########  #####     ### ####### #####   ### #######, #####   ######## ######  ##,###   ########## ########### / ###.######## ##.####### / ##.####### ###.##### #### ####### ######  #####  ####     #####    ## ######## ### ####### # ######### ####. ### ### ########## #### ######## ### #### ###########.\n ### #### ##### #######, ########### ###### ### ######### ###### ### ###### ### ### ##### ## #### #### ### ###.\n ### ######## ######### ### ########## ########## ###### ### ### ## #### ## #### ## ### ####### ##########.\n ### ####### ######, ### #### ####, ### ####### #####, ### ###### ####### ### ###### ### ### ## #### ## #### ## ### ####### ######.\n ### ######### ####### ### ######## ## # ############ ## ### ######## ######### #########. ####### ## ####, ### ### ####### ######## ### ## ###### ### #### ######### ## ### ######## ######### #######. ### ####### #### ##### ## ### ####### #### #########. ### ### ####### ######## #### ########### ## ####. ### ######### ####### ######## ### ###### ## ####.\n  \n ####### ###### ######### ### ###### #####, ##### ##### ######## ##### ## #### #########. ######## ##### ##### ### ######## ##### ## ######## ####### ########### ########, ##### ### ###### ######### ### ##########, ####### ### ####### ### ### ######## ####### ######, ### ######### ### ###### ###### ###### #### # ##### ######## ##### #### ##### #### #### ##### ### ####### ######. ##### #### ### ####### ## ###### ####### #### #### #### ### ##### ## ########## ## ### ### # ######. ##### ######## ####, # ###### ## ######### ########## ##### ### ####. ######### ####### ### ######### #### ## ####### ######, #### ## ### ###### ###### ### ########. ### ### ####### ###### ###### ## ### #### #### ## #######. \n ###### ### ####### ######, #### #### ##### ## #####, ## #### #### ### ####. # #### ##### ######### ## ### ### ######## #### ##### # #### ### ######. #### #### ##### ### ## ### ##### #### ### ##### ### ######### ## ### ########## #### ##### ### ######, ### ### ######### #### ##### ##### ##### ### ######. #######, #### #### ##### ### ### ##### ## ### ##### ########## ##### ###### ### ######. #### ############ ######### ##### ### ######## ## ######## #### #### ####### ##### #### ### ## ############# ## ### ### ## ####. #### #### #######, #### #### #### #### ###### ## ##### ####### ##### ######## ### ##### ####### #### ########, ## ## ####, ## ## ### #####, ### ##### ####### ### #### ## ##### ########## ### ##### ####### #### ########, # ## ####, # ## ### #####, ### ### ##### ####### ### ##### ########## ### ##### ####### #### ####, # ## ####, # ## ### #####. \n ### ### ## ### ## #### ### ## ### #### ##### ############ ###### ####### ## ### ###### ###### ### ###### ## ##### ##### #### ##### ##### #### ###### ### ####### ###### #### ##### ##### ### ######## ###### #######. #### #### ##### ### ###### ##### ##### #### ## ##### #### ##### ######. #### #### ## ####, ### ### ### ### ########### ## ##### ### #### ### ## ### #### ##### ####### ## ##### ### ##### #### ##### ##### ####. \n ### ### ## #### ### #### ###### #### ######### ######### ##### ## ######### ###.#### ### ###### ### #### ####### ##### ######### ## ### ####### ##### ####,#### ###### ### ##### ######### ### ##### #### ### ######### ##### #######.#### ##### ###### ## #### ### #### ######## #### ## ### #### ##### ### #######.############ ######### ## #### ####### ### ### ## ##########, ## ### ####### ## #### ### ##### ### ##### ### ## ####### ########## #### ######.######## ##### ###### ## #### ### #### #### #### ## ### ############# ##### ###### # ########## ######. \n ## ########, ### ####### ###### ###### ## ######### ### ###### ### ######## ####. #### #### ########## ### ###### ######, ######, ### ## ### ########, ### ### ### ############ ## #### ########## ### ##### ########. ### ##### ######### ### #### ## ### ####### ########. ####### #### ## ###### ### ######### ## #########. ####, ### ### ############ ## #### ########## ##### ##### ### #### #### # ###### #### ## ########. ### ### ########### ## ### ###### ##### ##### #### ### ## #####. ### ###### #### ### #### ########### ###### ### #### ## ######## #### # #### ### #####. ##### ########### ## ### ######## ##### ####### ### ###### ##### ######### ########### ###### ##########, ##### ### ### ####### ### ########### ####### ## ### ### #### ## # ###### ########## ####, #### ### ####### ###### ####### #.#. ####### ####### ##### #### ### #### ## ### ###### ### ###### #########, ##### ####### ####### ## ###### ## ######## ###### ########## ## ########, #######, ### ######### ## ### ####### ##### ### ##### ##### #######, ##### ####### ####### ## ##### ### ####### ###### ## ########### ##### ##### ## # ##### ##### ### ### ### #### #### #######, ##### ####### ####### ## #### ### #### ## ### #### ############ ### ######### ## ### ######. ##### ##### ########### #### ####### ##### ##### ####### ### ##### ## ### ####### ######## ### #### #### ### ###### ######. \n ####### ##### ### ######## ##### ## ### ##### ########, ##### ## ### ## #### ## ### #### ######## ## ### ###### ######## ## ######### ## ### ####### ####.#### ##### #### ####, ##### ### ### ####### ## ######## ####### #### #### ##### ### ### ######### ## ### ######, ######## #### ### ##### #### ### ####### #######. ##### ###### ### ##### ######### ##### ###### ### ####### ########, ###### #### ### # ###### #### ### ####### ########. \n ###### ### ###### ## #####, ### ####### ###### ####. ## ## ###### #### #### #### ###### ###### ### ########## ######, ## #### ## ### ######### ## ### ########, ###########, ########### #####. ### ##### ### ## ### #### ##### ## ##### ## ### #### ###### ###### ### ### ##### ##### #### #### ##### ###### ### ### ##### #### ###### ##### ########. ### ###### ## ### #### ##### ## ####### ## ### #### ########### ########## ######. ### #### ######## ###### ##### ## ####### ## ### ###### ### ## ###### ## #### ##### ### #### ########### #### ### ######## ######. ### ######### ###### ## ### #### ##### ## ####### ## ### ######## #### ########. ### ##### ## ### #### ##### ## ####### ## ### ##### #### ### #### ### #### ######## ########## ## # ####. ### #### ######## ###### ##### ## ##### ## ### ###### ###### ### #### ######## ### #### ##### #### ######. ############, ######## #### ###### ## ########## #### ###### ########### ######### ## ### #### ##### ## ### ####### ####### ### ## ######## ## #### ######### ### #### ### ### ### ####### ## ### #########. \n ### ########### ##### ### ### ####### ####, ### ############# ####, ### ### ########## ##### #### ######## ## #### #######. ##### ### ##### ####### #####, ########## ## ### ### ####### ## #### ########, #### ########## ###### ##### ### #### #########. ##### ### ### ############# #####, ########## ## ### ### ######### ## #### ########. ##### ### #### ### ########## #####, ########## ## ### ### ########## ####### ########## ## ########. \n ######## #### ######## ### ######## \n ### ### ######## ##### ## #### #####, #### ### ### ##### ##### ## #### ##########, ########## ## ########## #########, ######### ### ### ############. ##### ### ####### ## ###### ##### ## ############## ###### ##### # ########## ###### #### ## #######. \n ###### # ###### #### ###### ####### ##########. ##### ### ##### #### ###### ### ######## ####### ####### ### ###### ####, ### ###### #### ##### ### ####### ####, ### ##### #### ##### ### ##### ####, ### ### ###### #### ##### ### ##### ####, ###### # ###### #### ##### # #### ##### # ###### #### ## ### ##### #####. ### #### ## #### ###### #### ### ###### ###### ### #### ##### #########, ######### ### ##### #####. ###### ### ###### ####### ### ####### ############# ###### ### ### ####### ######, #### ##### ####, ### #######, ## ### #### #### ######## ### # #### ### # ###### ###### #### ### #### #### ### # #### ### ###### ## # ########## #############, ### # #### ##### #### #### ##### #########, #### ###### ### ##### #### ### # ###### ####. #########, ### #### #### ### #### ####### ###### ###### ## ### ###### ## ########## #### ##### ######### ## ##### ###### ## #####. ### #######, ## ####, ### ###### ####### ### ## ##### ### ######## ### ######### ######## ### ### ## ####. ##### ######## ### ### ## #### ### ####### ########, ### ### ## ##### ### ######## ###### ## ### ####### ########. ######## ###### ### ### #### ###### ########, ### ######## ### ########## ######### ### ### ### ###### ## #. \n ### ######## ###### # ########## ######. #### #### ##### ## ######## ## # ############# ######, #### ### ##### #### ## ### #### ##### ######### #### ### #### #####, ##### ### ##### #### ## ########## #### ### ########. ## ### #### #####, ### ########## #### ##### ####### ####### ######### #### ## ### #### ##########. ### ### ### #### ## #### ########## ### ########## #### ### ########. ##### ### ### #### ### ####### #####, ### ####### ####### ## #### ########## #### # ########### ######, #### ### ###### ## ### ###### ######## ### ### ### ### ###### ##### ####### ### ###### ## ### ###### ######## ### ### ### ### ###### #####, ### ### ###### ## ### ###### ######## ### ### ### ### ###### ##### ####### ### ###### ## ### ###### ######## ### ### ### ### ###### #####. ## ##### #####, ### ######### ###### ####### # ######### ########## #######, ####### #### ### #### #### #### #### ##### ## ##### #, #, #, ### #, ##### ### ##### ##### ## #### ## ##### #, #, ### #. #### #### ## ####, ### ### ###### ######## # ##### #######, ####### #### ### #### ### #### ##### ## ##### #, #, #, ### #, ##### ### ##### ###### ## #### ## ##### #, #, ### #.#### \n ### ##### ####### #####, # ############# ###### ####### ### ####### ## #### ###########, ## ##### ## ### ### ######, ### ## #### ######## ## ####. ### ###### ## ### ### ###### #### ### ##### ####### ############ ######. #### ###### ### ##### ##################### ####### ### ### ####### ########## ### ####### #### ####### # ############ ####. ## ########, ### ###### ###### ### #### ####### ### ###### #### ######## ###### ##### ## ### #### ########## ###### ## ### ######. \n ### ###### ##### ##### ### ####### ######, #### ### ### ##### ##### ## #### ########## ######### ########## ## ########## #########, ## ### ####### ######. ##########, ### ### ##### ##### #### ## ### ######## #######.#### \n ############# #### ######## #### ## ### ######### \n ### ###### ####### #### ### ### #### ############# #### ## ### ###### ####. ### ###### #### ########## ######### ## ### ### ####### ######, ### #### ## ####### ############# ### ## ### #######, # ## ############. ######### ### ######, ### ### ####### ##### ### ###### ##### ######## ## ## ############, # ## ######## #### ### ############# ####. ### ### ####### ##### #### #### #############, ### ##### ####. \n    ##### ### #### ##### ####### ### ####### #########    ###### ####### ## # ##  ####, ####, ####, ####, ####, ####, ####, ####, ####, ####, ####, ####, ####, ####, ####, ####, ####   ####, ####, ####, ####    ###########/### ####### ###### ## ## ##  ####, ####, ####, ####, ####, ####, ####, ####, ####, ####, ####, ####, ####, ####, ####, ####   ####, ####, ####, ####, ####, ####, ####, ####, ####, ####, ####, ####, ####, ####, ####    ############/### #########/###### ##### ######## # # ##  ####, ####, ####, ####, ####, ####   ####, ####, ####, ####    ####### ##### # # #  ####, ####, ####, ####, ####, ####  #    ### ####### ##### # # #  ####, ####, ####, ####, ####   ####    ######## #########/############ ##### # # #  ####, ####, ####   ####, ####, ####, ####, ####, ####    #### #####/####### ####### # # #  ####, ####, ####   ####, ####, ####, ####    ##### #### # # #  ####, ####, ####   ####, ####    ### #### ###### # # #  ####, ####   ####, ####, ####, ####, ####, ####    ####### ####### # # #  ####, ####   ####, ####    ######### ######### # # # ####  ####, ####, ####, ####    ##. #####/####### ##### # # # ####  ####, ####, ####     #########/########## ####### #### ########## ########  # # # ####  ####, ####, ####     ####### ###########/######## #### #######  # # # ####  ####, ####, ####    ######## ##### ####### # # # ####  ####, ####    ######### ##### # # # ####  ####    ###### ######### # # # ####  ####     ######### ####### ########## ####### ## #####  # # # #### #     ######### ###### #### ########## ######  # # # #### #    ####### #### # # # #  ####, ####     #### #### ######### ### ####### #####  # # # #  ####, ####     ### ###### #### #### ######## #####  # # # #  ####, ####    ####### ##### # # # #  ####, ####     ####### ##### ####### ## #####  # # # #  ####     ########## ######## ####### ## #####  # # # #  ####    ####### ###### # # # #  ####     ####### ##### #### #### ## ### ###### ############ \n   ######### ####### ######### ######### ######## \n ###### #######\n  ### ####### ######## ######### ####### ######, ### ##### ######### \n  ####### ######### ######### ######### ########## \n ######### ############\n  ### ####### ######## ######### ### ####### #######, ### #######/######## #### ######## \n ####### #######\n  ##### ######## #### ######## ######## ########## ########### ## ########## \n ### ##### #### ## ####### ######## ########## ########### ############ \n ## ### ## ### ##### ###### ####### ## ##### #######, ### ### ### # #### ####### ## ############ #### ########## ######## ## ### ###### ######. ### ### ###### # ######## #### ###### ########## ####### ## ### ###### ######, ### ####### ######, ####### ### ##### #### ### ### ### # ######## ########## ###########. ####### ## ### ######## ######## ######, ### #### ## ########## ######## ### ## ### ###### #### ### ###### #### ### ####### ###### ##### ##### #, ########## ##### ###### #### ### ###. ######### ## ### #.#., ### ### ### # ######## #### #### ### ### ####### ### ####### ######. ##### #### ### ### ######### ########## ### ####### ##### #### ######## ###### ######## ######## ## ### #### ##### ### ##### ### #######. \n ############# ############ ### ######## ########## ########### ### ############ ############ ## ############# #### ############. #### #### ## #### ### ### ######### ###### ####### ### ########### ######### ## ### ########## ############## ## ########## ###### ## ### ########## ############. #### ########## ### ### ## ### ### ####### ##### #### ## ### ####.#### \n ###### ###### ### ########## ############ ## ####, # ###### #### #### ### ## ##,### ######, ######### ## ### ######## ## ### #### ### ### ####### ## ### ##### #### #### #######.#### \n ########## ############ ######### ## ######### ######, ## #### ### ### ### ### ######## ########, #### ## ####### ## ### ####### ##### ##, ### ### ##### ######, ##### #### ##### ###### ########, ## ## ####### ## #####, ### #### ## #### ### ## ### ##########. ## #### ### ### ####### ##### ## ##### ####### #### ## ####### ## ### ####### ##### ##### ### #### ##### ## ####### ## ####### ##### #####, ###### ## ### #### ### ##### ######## ##### #### #### ### #### # ##### ######## ########.#### \n ## ## ####, ### ##### ########## ####### ######## ##### ######, ### ###### ### ####### ######, #### #### ## ### ## ### ##########. ## ### #### #### ### ##### ########## ######### ## ## #######, ##### ######## ### ### ##### ##### ## ## ####### ### ##### ########## ##### ## # #######.#### \n ####### ###### ####### ############ ######## ######## ########## #### ## #### \n ########## ### ############# ####### ############ ############ ## ### ### \n   ####### ########, ######### #### #### ## ####\n  ###### #######, ######### #### #### ## #### ### ############ #### #### ## ####\n  ##### #######, ############ #### #### ## ####\n  ##### #####, ############ #### #### ## ####\n  #### ######, ############ #### #### ## #######\n  #######  ## ######## ####### ## ### #######\n  ##### ## ######## ########## ########### #######  #### ## ####### ### #######, # #### #### ## ########### ### ####### ### ### ### #### ### ###### ######\n \n  ####### ####### ############# ######### ####### ############ #### ## ####### ### ####### \n ######### ######## #### ##### ##### ######## ### ###### ######## ######### ### ###### ### ### ## ### #### #####, ## ########## ###### ## ############# ####### #### ##### ######## #### ####### ######### ## ### ##### ## ######## ## ### ###. ##### ## # ##### #### ## ####### ####### ### #### ### ### ###### ## #### #### ######### ########## ### ##### ############# ## ##########, ###### ######### ## ######## ###### ## ### ####### \n   ###### ########, ####### # #### ######## #### ### ######## ######## ########## #### ## ####, ####, ####, ####, #### ######## ###### ## ### ####, #### ### #### ##. ###### ###### ## ### ####, ### ## ### #### #### ##### ############ ### ########## ####, ###### ####### ###### ########, ##### ########, ######## ########, ## ######## ########## ############\n  ####### ############, ######### # #### ######## #### ### ######## ######## ########## #### ## ####. ##### ###### ##### ### ### ## ### #### ##### ######### ## #### ######## #### ### #### ### ## #### ####### ## ### ######, ####### ## #### ### ### ### ### #################### ## ### ###### ## ### #### #####.\n  #### #####, ####### # ###### ### ######## #### ####### ##### #####, ####, #####, #### ##### ### ##### ######, ##### ## #### ## ### ## ### ## ######## ########## ############ \n  ##### #####, ###### # ###### ####### ###### ########, #### ### ########, ###### ##### ########, ###### ######## ########, #### ##. ######, ## ######## ########## ############\n  ####### #######, ########### #### ######## #### ### ######## ######## ########## #### ## ####, ####, ####, ####, ####, #### ######## ###### ## ### ####, ####, #### ##. ###### ###### ## ### ####, ####### #### ######## ## #### #### ### ###### ##### ### ###### ######## ## #### ### #### #### #########, #### ### ########## ##### ####, ## ######## ########## ############\n  #### ##########, ###### # ### ######## #### ###### ######### ######, ### ## ### ########## ####, ###### ## ### ############## #### ## ### #### #### ##### ############, #### ######## ######, #### ### #### ##. ######, #### ### #### ### ########### ######## ########, ###### ### ######## ######## ## ####, ####### ### ### ## #####\n  #### ########, ######### ### ######## #### ###### ######### ######, ### ## ### #### #### ##### ############ ### ########## ####, ###### ## ### ############## #### ## ### #### #### ##### ############, ######### ### #### ######## ######, #### ##. ######, #### ### #### #### ###### ###### ## ### ####, #### ### ###, #### #### ####### ### ###### #### ######## ###### #####, #### ### ########### ######## ######## ### ####### ### ######## ######## ### ### ## #####\n  #### ########, ######## #### #### ######## ###### ##### ######, ###### ## ### ############## #### ## ### #### #### ##### ############ ######## ### ### ## #####\n  ### #####, ####### ###### ### ######## #### ### ####### ###### ##### ##### #####, ### #### ### ########, #### ### ###### ## ### ####, #### ### #### ##. ######, #### #### ##### ############ ###, #### ### #### ######## ### #### ###### ###### ## ### ####, ########## #### ###, ###### ## ### ### ########### ##### ## #### ######## ### ### ## #####\n  ###### #########, ######## #### ### ########, ########## #### ###, #### #### ###### ###### ## ### #### ######## ## ####, ###### ## ### ### #### #### ## #### ###### ######### ## ###### ### ## ### #######, ######## ## #### ## # ###### ## ### ######### ############.#\n  #### ######, ######## ###### ### ######## #### ### #####, #### ### ###### ###, ###### ######## ### #### ######## ###### ######## ### ### ## #####\n  #### ########, ########### ###### ### ######## #### ### ####### #####, #### ##### ### ##### ######, ###### ########, ## ######## ########## ############, #### ##### ## ### #### ###### ######## #### ######### ######## ## ####, ####### ### ### ## #####\n  ### ####, ####### #### ######## #### ### ######## ######## ########## #### ## ####, ##### #### ## ### #### ### ##### ### ###### ### ######## ####### ## ### ### #### #### ## #####\n  ####### #######, ######## ### ######## #### ###### ##### ######## ######,#### #### ##### ### ##### ###### ######## ### ### ## #####\n  ###### ########, ####### ##### #### ## ### #### ### ##### ## ### ####### ####### ######## ### ### ## #####\n  ####### #############, ######## #### #### ######## ###### ##### ######, ###### ######## ######## ### ### ## #####\n  ## #### #########, ##### #######, #### ### ### ### #### ### ################ #####, #### ######## #.#. ######## ###### ####### ## ### ###. ####### ######## #### \n  ######## ###### ######## #### ##### #### ## ####, ###### ########, ####### ########, #### ###, #### ### #### ###### ###, #### ### #### ######### ###### ## ### ####, #### ###### ## ####### ### ### #####, ######### ###### ## ### #### #####, ### ###### ### ##### ## ### #### ######, ### #### ## ######\n ######### ####### ####### ##### #### ### ######### ###### ## ### ####, ######## ###### ####### ## ### ###### ####### ## ### #### ### ##### ### ###### ### #########\n ######## ### ##### ##### ###### ####### ####, #### ### ########, ###### ## ##### ### ### ####### #######\n ###### ###### ######## ###### ### ##### ###### ## #### ### ####, ###### #########\n ######## ##### #### ##### ### #### ###, ###### #########\n ########### ### ####### ####### ######## #### ### ##### ## ### ###### ### ###### #####, #### ##### #### ## #####.\n ############# ########## #### #### ##### ###### ## ### ### ############# #####, ###### #########\n  ##### ####, ### ### ### ##### ########## ##### ## ########## ####### ## ### ### ###### #### ####, ### ##### #### ## ### ########## ######## ####. \n ### ####### ###### ###### #### # ###### ## ############# ####### ## ### ####### ##### #######, ############ ## ######### ### ########## #### ### ## ### ########## ### ### ####### ############### ####### ## ##### #### ####### ### ## ###### ###### ### ##########, #.#. #### ##### ##### \n  ####### #### ## #.#. ########### #### ## ###### #### ### ### #.#., ###### #######, #### ####### #### ###### ### ######, ### ####### ## ############### #### ###### #### ### #.#. ######## ## #####, ### ### #### #### ########### ### #.#. ## ############# ########### ##### #######.\n #.#.##### ####### ### ### ####### ## ############### #### ## #### #### #### #### ########### ## ####### ####### ### ######### #### ####### ###############, #### ## ###### ####, ### ##### ######.\n  #######  #### ## ####### ######## ########## ########### #### #######\n #### ## ######## ########## ########### #### #######\n #### ## ######## ########## ########### ##############\n #### ## ### ############ #### #######\n #### ## ####### ### #######\n ### ## ####### ## ### #######\n  ### ####    ########## ###### \n  ######## ########## ########### ###### \n  \n  #### ## ######## ### ######## ###### ## ###### ## ##### ############ ###### ##########\n #### ## ########## ####### ## ######## ############ ###### #######\n #### ## ### #########\n #### ## ######## ########## ########### ######\n #### ## ######## ########## ########### #######\n #### ## ############ ###### ##### ## ### ###### ###### ### ######\n #### ## ## ####### ### ##### ###### ##### ## ### ###### ######\n ##### ############ ###### ####### ## ### ###### ###### ### ######\n ######## ########## ########### ############\n ######## ########## ########### ####### #######\n ######## ########## ########### #########\n ### ###### ###\n #### ## ### ######## ######\n ### ###### ######\n   ##########   ### # ###### ######### ### ### ########### #######\n  ####### ######## ########## ########### ######\n  #############  ########## ### #############\n #####\n ####### #######\n  ###### ############  #### ###\n #########\n  ####### ####### ###### ### ##########\n ####### ##########  #### ## ### ######### ########### ########\n #### ## ### ######### ########### #######\n  ##### ### #####\n ########## ########  ###\n ###\n ####\n ##### ######\n ### ##\n ###\n ###\n  ##### #####  ### ##\n ### ##\n ### ##\n ### ### ### ######\n ### ##\n ### #######\n ### ######## ###### ###\n ### ######## ######\n ### ######## #######\n ### ########\n ### #####\n ### ###\n ### ####\n ### ######### ### ## ###\n ### ######\n  \n ##########    # # # #######, ####### ######### #, #####. #### ### ## ##### # ### #######. ###.###. ### ##### ########, ###. ######### ##### #, ####. ## #### #, ######## ##### ## ### ### ##### ### ######## ## ########, ####### ### ###### ##### ### ##### #### #### #### ## ########## ###### ### ########## ########### ## ####### ###### # ####### ## ### ###### ######### #####, #### ## ##### ####### #######. \n  # ######## ## ### ###########. ### ##########. #### ##, ####. ######## #### ### ######## ## #### ##, ####. ######### #### ##, ####. \n  # ########## ### ####### #### #### #####, ### #### ##### ## ## ##### ### #### #######. ####################.###. ### #, ####. ######### #### ##, ####. \n  # ######, ####. #### ### ## ### ############## ###### ###### ## ### ######. ######## #######. ######### ### ##, ####. \n  # ########, ###. #### ##### #####. ###.###. ### ##### ########, ###. ######### ##### #, ####. \n  # ######## ## ########## ## #######. ###.###. ### ##### ########, ###. ##### #, ####. ######### ######## ##, ####. \n  # # # ### ######## ### ########## ############. ####### #####. ####. #.###. ##################. \n  # #### ## #####. #######. ######### #### ##, ####. \n  # # # ########, ### ###### #, #####. ####### #### ###### ######, ##### ################ ## #### #### ### ####, #### ## ###. ###### #### ####. Archived from the original on March 12, ####. ######### ##### ##, ####. \n  # #### ####### ###### ######, ## ######### #####, #### #########. ##############. ##### #, ####. ######### ##### ##, ####. \n  # ####### ######### ##### ########## ##### ###### ###### #####. ### #### #####. ##### #, ####. ######## #### ### ######## ## ######## #, ####. ######### ##### ##, ####. \n  # ######### ###### ### ##### ### #######. ######.###. ### ##### ########, ###. ######### #### ##, ####. \n  # #### ##### ########. ###.###. ### ##### ########, ###. ### #, ####. ######### #### ##, ####. \n  # ############# #####. #######.###. ### ##### ########, ###. ######### ######## ##, ####. \n  # ########, ####### ######. #### ### #### ## #### ####. ### ##### ###########. #.####. ######################. \n  # #####, ##### ###### ##, #####. ##### ###### ### ########## ### ## ###### #### ## ####. ### ####### #####. ######### ### ##, ####. \n  # ### #### ###### ############.##. ######### ### ##, ####. \n  # ######## ###### #########. ###.###. ### ##### ########, ###. ######### #### ##, ####. \n  # ######, ##### ######## ##, #####. #### ##### ## #### ### ####### #####. \n  # # # #####.### # ############ # ##### ##### ### #### ### ## ####. ###.####.###. ######### ##### #, ####. \n  # ##, #### ## #####. #### ## ######## ####### ## ###### ########. ### ######. ######### ##### #, ####. \n  # ####### ###### ######### ## ## ####### ## ########. ### ####### #####. ###### ##, ####. ##############. ######### ##### #, ####. \n  # ##### # ###### ######## ##### ## # ######## ### ######### ## ## ## ###.# ########. ### ####### #####. ######## #, ####. ##############. ######### ##### #, ####. \n  # #####, #####. #### # ############ ## ### ####### ####### ########. ######## ######. ######### ##### #, ####. \n  # ###### ##### ####### ###### ### ############, #####. ######. ######### ##### #, ####. \n  # ###### ##### ###### ## ###. # ####### ### ### ########. ### #####. ######### ##### #, ####. \n  # #### ############ ##### ###### ###### #####. ###.###. ######### ##### #, ####. \n  # #########, ######. ##### ##, ##### ########## ##### ####### #### ####### #######. ##############.###. ######### ##### #, ####. \n  # ########, ### ######## ##, #####. #### ####### #########, # #### ##### ### ##########. ### ### #### #####. ##############. ######### ##### #, ####. \n  # ##### #### ## ### ### ####### ## ######, #.#. ## #####. ####.###. ### #, ####. ######### ##### #, ####. \n  # #### ### #### ###### #### ### ## #######. #######.#######.###. ######### ##### #, ####. \n  # ####### ######, ##### ### #####!#. ###.#######.###. ######### ##### #, ####. \n  # ########### ####### ##### ##### ### ### ######## ### ##### # ################.####. ###.################.###. #### ##, ####. ######### ##### #, ####. \n  # #####, #####. ###### ### #### ###? ### #### ##### #### #### ######### ####### ###########. ######## #######. ######### ##### #, ####. \n  # ### ##### ## ######### ### ##### #### ## ##### ######. ####### #########. ######### ##### #, ####. \n  # ###### #### ##. #### ### #### ### ### ## #### ## #### ######?#. ### ###### #######. #### ##, ####. ######### ##### #, ####. \n  # #### ############ #### ###### ####### #######, ### #### ## #### ######## ######. \n  # #####, ####### ######### #, #####. #### ############## ####### ## ### #.#.#., ### ####### ### ### ##########. ### ### #### #####. ##############. ######### ##### #, ####. \n  # ######, ###### #### ##, #####. ### #.#.#.#. ##### ### #### ######, ### ####### ###### ### ##### #####. ### ### #### #####. ##############. ######### ##### #, ####. \n  # # # ####, #### ##### ##, #####. ############ #### ##### ####, ### #.#.#. ###### #### ### ########. ### ### #### #####. ##############. ######### ##### #, ####. \n  # #######, ###### ##### ##, #####. ######## ## ## ########## ##### ### ### ########. ### ########. ######### ##### #, ####. \n  # #######, ######## ############.### ##### ##, #####. ### #### ### ## ### ####### ######## ### ##### ### ##### ##### ### ############ ## ##### ####. ### ####### ############. ######### ##### #, ####. \n  # #######, ### ##### ##, #####. ############ ###### ##### ###### ## #### ### ######. #####! ######. ######### ###### #, ####. \n  # ########, ### ######### ##, #####. ####### ##### ## ######## #####. ####. ######### #### ##, ####. \n  # #######, #### ##### ##, #####. ####### #### ####### ## #### #, ### #### ######. #####! ######. ######## #### ### ######## ## ###### #, ####. ######### #### ##, ####. \n  # #####, #### ######## ##, #####. #### ####### ##### # ##### ## #######. ####. ######### ####### ##, ####. \n  # ##.#.#. ###### ### ####### ###### ##### #####. ### ### #### #####. ######## #, ####. ######### ######## #, ####. \n  # # # #####, #### ######## ##, #####. ####### ## ####### ####### ## ### ####### ## ##### #######. ######### ######## #, ####. \n  # #### ####### ####### ### ############# ####### #### ###### ## ######### ### ############. ###.### ###### ########. ### ##### ########, ###. ####### ##, ####. ######### ######## ##, ####. \n  # ########### ##### ########## ### # #######. #######.###.###. ### ##### ########, ###. ######### ######## ##, ####. \n  # #### ########## ### #### #####. ###.###. ### ##### ########, ###. #### ##, ####. ######### ######## ##, ####. \n  # #####, #### ######### ##, #####. ######## #### #### ###### ## ###. ##. ####. ######### #### ##, ####. \n  # #####, #### ######### #, #####. #### #### ########### ####### ### ######. ####. ######### #### ##, ####. \n  # #####, ##### ##### ##, #####. #### ####### #### ## ### #### ### #### ## #### ####### ######## ## ########. ## ######. ######### #### #, ####. \n  # ####### ##### ############# ### ####### ## ### #####, ####. #### ##, ####. \n  # ##### ############ #### # ## ##### ## ####### ############. #### ##, ####. ######### ######## ##, ####. \n  # ######, #### ###### ##, #####. ###### ##### ### ### ######### ####### ### ### #### ##########. ######### ####### #, ####. \n  # #####, ###### ######. ########## ### ###### ############ #### ##. ######### ####### #, ####. \n  # #### ##### ## ######### ####### ###### #### ## ######## #### ####### ########## ## ###########. ###.###. ### ##### ########, ###. ##### ##, ####. ######### ######## ##, ####. \n  # #### ############ ##### ##### ######### ## ########## ####### ###### ### ### #### ## ########. ###.###. ### ##### ########, ###. #### #, ####. ######### ######## ##, ####. \n  # #########, #### ######## ##, #####. ######## #### #### ########, ########### #####. ###.###. ### ##### ########, ###. ######### #### ##, ####. \n  # ####, ######## ##### ## ######## ####, ###### ########. ###.###. ### ##### ########, ###. ########## #####. ####### ##, ####. ######### #### #, ####. \n  # ########, ##### ######## ##, #####. #### #### ## ###### ### ####### #######. ####. ######### ###### #, ####. \n  # #### ####### ######## ########## ##### ### #########. ########.###. ### ##### ########, ###. ##### ##, ####. ######### ######## ##, ####. \n  # ########## ####### #### ####### ## ##########. #######.###. ### ##### ########, ###. ### ##, ####. ######### ######## ##, ####. \n  # ######### ##### ######## ###### ### #### ## ### ####. ###.###. ### ##### ########, ###. ########## #####. ##### ##, ####. ######### ##### ##, ####. \n  # ###### #### ###### ###### ##### ###### ### ##########. ###.###. ### ##### ########, ###. ########## #####. ###### #, ####. ######### ##### ##, ####. \n  # # # #####, #### ####### #, #####. ###### ###### ### #### ## ######. ####. ######### ##### ##, ####. \n  # #######, ##### ###### ##, #####. #### ## ##### ####### ###### ############ ## ########. ###.###. ### ##### ########, ###. ########## #####. ######### ##### ##, ####. \n  # ############# ##### ### ####### ######## ##### ###### ########### ## ##### ######## ############ #######. ######.### ###### ########. ### ##### ########, ###. ### ##, ####. ######### ####### ##, ####. \n  # ## ##### #### ## ### ##### ######### #####. ###.###. ### ##### ########, ###. #### #, ####. ######### ######## ##, ####. \n  # ########, #### ##### ##, #####. ####, #### ###### ### ######## ### ####### #######. ###.###. ### ##### ########, ###. ######### ######## ##, ####. \n  # # # #########, #### ######### ##, #####. #######, #### ### #### #### ## ######### ### #####. ###.###. ### ##### ########, ###. ######### ######## ##, ####. \n  # # # # #########, #### ######### ##, #####. ########## ##########. ### ######### ###.# ################. #.###. \n  # # # # ######, ### ######### ##, #####. ########## ### ####### ##### #### #### #########. ###.###. ### ##### ########, ###. ######### ######## ##, ####. \n  # #### ####### ######## ###### ##### #####. ###.###. ### ##### ########, ###. ######### ####### #, ####. \n  # #### ###### ###### ###### ###### ## ##########. ###.###. ### ##### ########, ###. ########## #####. ####### ##, ####. ######### ##### ##, ####. \n  # #### ## #### ####### ##### ## #### ########## ## #######. ###.###. ### ##### ########, ###. ########## #####. ######### #, ####. ######### #### ##, ####. \n  # #### #### ########## ############ ## ##### ## #####. ####. ######## #, ####. ######### #### ##, ####. \n  # ######## ####### ##. ####### ####. ####### ## ##### ####### ###### \n  # ########, #####. ###### ###### #### ### #######/#######/###### ####?#. ######### ######## #, ####. \n  # ######//##############.###/####/##/##/###############################/ \n  # #########, ##### ##### ##, #####. ######## ####### ##### ### ####### ## ###### ##### ######## ###### ######### ######### ## #######. ##### ####. ######### ####### ##, ####. \n  \n ####### #######   #####, ####### ######. ### ##### ######## ### ########## ##### ## ### ##### ## ### ###. ########### ############. ##################. \n  ####### ## ###### ########### ######. ###### ############ ### ########## ####. ###### ###########. ##################.### ###### #### ####### ######### ###### \n  ########, #### ######. ##### ######## ### #######. ##. ##################. \n  ########, ###### #. ######. ##### ## #### ###### ### ############ ##### #####. ######## ########## ## ######## #####. ##################. \n  ######## #####    ######### ####### ### ##### ####### ## ######## ########## ###########.      ######### ### ########## ####### ### ######## ########## ###########      ######## ####### ### ###### #### ### ## ######## ################ ####### #### # #### ######### ###########, #### ######## ## ####### ####### ##### #######. ######### ################ ########, #### ## ##### ### ############ #### ######## ##### #######, #### ##### ### ######, #########, ######, #####, ### #######, ### ### ###########.\n \n ######## ########## ####### ###########\n ######## ########## ######## ###########\n ### ##### ### ########## ########## ##### #######\n ### ##### ### ############ #######\n     #\n #\n #\n \n ######## ########## ###########\n   #######\n##########  \n   ########   ###### ####### ######## #### ### #### ###### ############ ##### ####### #######  \n   #######   ####### ##### ######### ######### ####### ####### ####### ###### ######### #####  \n   #########   ####### ##### ######### ####### ##### #### ####### ##### ########## #######  \n   \n    #######\n##########  \n   #########   ###### ####### ######### ############ ######## #### ####### ######## ##### ####### #### ####  \n   #######   ###### ##### ######## ### ####### ######## ### ####### ###### ####### #### ########## #####  \n   #########   ###### ######### ####### ####### ####### ######### ### ####### ######## ### ####### #####  \n   \n    ###### ######    ##### ###########  ###### ###### ######### ###  ######## ####### ####  ###### #####  ######## ####   ###### #########   \n   #######   ############  ### ###  ### ######     ########## ### ############# #### ### ####### ####### #######  ######## ####### #######  ####### ###### ########### ######## #### ######## #######    \n   #############    #######  ####### ####### ####### ####### #### ### ######### ##### ####### ##### ##### ####### #### ####### ####### ###### ## ######### ####    #### #######  ####### ############## ######### ####### ####### ####   ###### ########  \n   ###### ### ######   ##### ####### ######  ### ######  ### ### ###### ### ######## #### ###    #### ## #### #######  ### ###### ########### #### ### #### ########### #### ## ######## #######  \n   ######   ###### ########  ########## ########## ######### ###### ### ### #####   #######  ############ ####### ##### ####   # ###### ####### ######## #####  ## ### ##   ######### #####  ####### ######### ######### ########   #### ########## ## ### ###### ######  \n      ########    ######  ##############  \n \n  ##### ## ####### ########\n     #\n #\n #\n \n  ####### ### ###### ## ####\n    #####\n ###### ######\n ######## ####\n ########\n ######\n ############\n # ######\n  \n  #######  \n   ########   ######\n ########\n ### ####\n ############\n #######\n  \n   #######   #######\n #########\n #######\n #######\n #########\n  \n   #########   #######\n #########\n #####\n #######\n ##########\n  \n   \n    #######  \n   #########   ######\n #########\n ######## ####\n ########\n ####\n  \n   #######   ###### #####\n #.#. ########\n #.#. ######\n #######\n ##########\n  \n   #########   ######\n #######\n #######\n ### #######\n ### #######\n  \n   \n   \n    #\n #\n #\n \n ### #######\n   #####                 #######   #######   #######  \n   #####   #######   #######   #######   #######   #######   #######   #######   #######   #######   #######  \n   #####   #######   #######   #######   #######   #######   #######   #######   #######   #######   #######  \n   #####   #######   #######   #######   #######   #######   #######   #######   #######   #######   #######  \n   #####   #######   #######   #######   #######   #######   #######   #######   #######   #######   #######  \n   #####   #######   #######   #######   #######   #######   #######   #######   #######   #######   #######  \n   #####   #########   #######   #######   #######   #######   #######   #######   #######   #######   #######  \n   #####   #######   #######   #######   #######   #######   #######   #######   #######   #######   #######  \n   #####   #######           \n  \n    #\n #\n #\n \n ### ######\n    ##### #######\n ##### #######\n ###########\n ########### #####\n ##### ####### #####\n #### ###### ########\n ######### #######\n ####### ##### ####\n #### #####\n #### ### ######### #####\n  \n  #####         #### #### #### \n   #####  #### #### #### #### #### #### #### #### #### #### \n   #####  #### #### #### #### #### #### #### #### #### #### \n   #####  #### #### #### #### #### #### #### #### #### #### \n   #####  #### #### #### #### #### #### #### #### #### #### \n   #####  #### #### #### #### #### #### #### #### #### #### \n   #####  #### #### #### #### #### #### #### #### #### #### \n   #####  #### #### #### #### #### #### #### #### #### #### \n   #####  ####          \n   \n  ######### ######\n  ###  #### \n \n  #### \n \n  #### \n \n  #### \n \n  #### \n \n  #### \n \n  #### \n \n  #### \n \n  #### \n \n  #### \n \n  #### \n \n \n  \n  \n    #\n #\n #\n \n ##### ############ ###### ####### ## ### ###### ###### ### ######\n    ######## ######## ######\n ##### ###### ########\n ##### ###### ######\n ######## ########## ###########\n ######## ######## ######\n ######## ###### ######\n  \n \n    #\n #\n #\n \n ##### ############ ########## ####### \n    ####\n ######## ########## ###########\n ### ## ############# #####\n #### ################ ###\n  \n  ######   #######\n  ###### ###\n \n ####### ####### ########\n #####\n #######\n #####\n #######\n ##########\n #######\n ######\n #######\n ##### ######\n #######\n ######\n  \n   ########    ######### ###\n \n #######\n  ###### ###\n \n ######\n #####\n ########\n ####\n ######### ########\n #######\n  ###### ########\n \n #########\n ######\n ########\n ####\n ###### ####\n  ###### ###### ### # ######\n \n #######\n #########\n  \n   ####   #######\n  ##### ###\n \n #### ####\n #####\n #########\n ####\n ####\n #####\n ######\n ##########\n ######\n #######\n ########\n ########\n ####\n ###########\n #####\n ##### ######\n #########\n ##### #####\n #####\n ######\n ########\n ###### #### ########\n #######\n  \n   ######    ####### ###\n \n  ####### ###\n \n #######\n ##########\n #######\n #######\n  ###### ### ########### ###\n \n ########\n #######\n  ###### #####\n \n ##### ########\n #######\n #######\n #######\n  ###### ###\n \n #######\n  #######  ###\n ###\n  \n  ##### #######  #######\n ########\n  \n  ###### ###\n \n #######\n #######\n #######\n  ######  ###\n ###\n  \n  #####  ###\n ###\n  \n  ###### ###\n \n ######\n  ######### ###\n \n ##########\n #########\n #####\n #######\n ##########\n ###########\n ######\n  ###### ###\n \n  ######## ###\n \n #######\n  ###### ###\n \n  ######  ###\n ###\n ###\n  \n ########\n ########\n  #####  ###\n ###\n  \n  ###### ###\n \n  ########### ###\n \n  ######  ###\n ###\n  \n #######\n  \n   #######   #########\n ### #######\n  \n   #############\n###########  \n   ######  ####### ######### ###\n \n   ########   ######## ######\n #### ############\n ###### ##########\n  \n   ####   ##### ######### ###\n ##### ######\n #### ######### ###\n  \n   ######   ##########\n #######\n ######### ######\n #### ###### ###\n  ######## ###### ###\n \n #### ##### ###\n ###### ######\n  \n   \n    #######\n###########  \n   ########   ### ######## ############\n ##### ######## ############\n #########\n ######\n #####\n ###### ######  ###\n ###\n ####\n  \n #######\n  \n   ####   ### #### ############\n #####  ## ######\n ###\n ####\n ###\n  \n  \n   ######   ###########\n ####### ###\n ##### ###\n #############\n ####### #########\n ###### ######\n ####### ######## ######\n ##### ######## ######\n ##############\n #######\n ######\n  ###### ### ########## ###\n \n #####\n ###### #####\n ######\n  ########## ###\n \n  \n   \n      ######## \n \n \n \n \n   ######### #######     #### ########### ######\n #### #########\n ##### #### #### #### ####\n ##### #########\n ############ ####################################\n #### #############\n ###### #########\n ##### #########\n  ######## ########## #### ###### #########\n  \n \n    \n  \n ######### #### #######//##.#########.###/#/#####.###?##########################################################\n   ###########  ######## ########## ###########\n #### ############## ## ### #### #######\n ########## ####### ## ######\n ########## ####### ## ### ###### ######\n ##### ##########\n ############# ##### ## ### #### ####\n ############ ###### ####### ## ######\n ############ ###### ####### ## ### ###### ######\n ###### ####### ########### ## ####\n  \n ###### ###########  ##### #### ######### ####### ######\n ######### ##### ############## ####### #########\n Wikipedia indefinitely move-protected pages\n Articles with short description\n ### ### ##### #### ####### ####\n ### ######## #### ######### ##########\n ######## #### ######### ########## #### ##### ####\n ##### ## ###########\n ########## ########## #####\n ######## #### ###\n ### ###### #### ####### #########\n ####### ######## #### ## ## ########\n ######## ####### ######### ## ######## ### #########\n Wikipedia articles with BNF identifiers\n Wikipedia articles with GND identifiers\n Wikipedia articles with #### ###########\n ######### articles with LCCN identifiers\n Wikipedia articles with MusicBrainz identifiers\n Wikipedia articles with ### identifiers\n Wikipedia articles with SUDOC identifiers\n Wikipedia articles with VIAF identifiers\n Wikipedia articles with WorldCat-VIAF identifiers\n  \n \n \n \n \n  Navigation menu   Personal tools  Not logged in\n Talk\n Contributions\n Create account\n Log in\n  \n   Namespaces  Article\n Talk\n  \n    Variants    \n \n   Views  Read\n View source\n View history\n  \n   More   \n   Search     \n  \n \n \n  \n  Navigation   Main page\n Contents\n Featured content\n Current events\n Random article\n Donate to Wikipedia\n Wikipedia store\n  \n \n  Interaction   Help\n About Wikipedia\n Community portal\n Recent changes\n Contact page\n  \n \n  Tools   What links here\n Related changes\n Upload file\n Special pages\n Permanent link\n Page information\n Wikidata item\n Cite this page\n  \n \n  Print/export   Create a book\n Download as PDF\n Printable version\n  \n \n  ## ##### ########   ######### #######\n ########\n  \n \n  #########   ########\n #######\n ########\n #########\n ############\n ##########\n ##########\n ########## ##############\n #########\n ########\n #########\n ######\n #######\n #######\n #####\n #######\n #####\n ########\n #######\n #########\n #########\n #######\n #####\n ########\n #####\n ######\n #######\n ######\n ###/##########\n ###\n #######\n ##############\n ######\n ########\n ###### #########\n ########\n ########\n #####\n #######\n #######\n #########\n #####\n ########\n ##############\n ########\n ######\n ##########\n ######\n #####\n #########\n ########\n ###############\n ######\n ##########\n ###\n ##########\n #####\n #######\n ######\n ######\n #########\n ######\n #######\n #####\n #####\n #########\n ###### #######\n ##########\n ###########\n ###### / ######\n ############## / ##############\n #####\n #######\n #######\n #####\n #######/#######\n ###\n ######\n ######\n #########\n ##########\n ######\n ##### ####\n ##########\n ##\n ######\n ##\n ##########\n \n  Edit links\n \n \n \n \n    This page was last edited on ## ##### 2019, at ######(UTC).\n Text is available under the Creative Commons Attribution-ShareAlike License; additional terms may apply. By using this site, you agree to the Terms of Use and Privacy Policy. Wikipedia is a registered trademark of the Wikimedia Foundation, Inc., a non-profit organization.\n   Privacy policy\n About Wikipedia\n Disclaimers\n Contact Wikipedia\n Developers\n Cookie statement\n Mobile view\n     \n   \n  \n ","pages":{"startPosition":[0,4990,10001,14999,20000,25000,30000,34999,39996,44998,49998,55001,59997,65000,70001,74995,80000]}},"html":{"comparison":{"identical":{"groupId":[0,0,0,0,0,0,0,1,1,1,1,1,2,2,2,3,3,3,3,3,4,4,4,5,5,5,6,6,6,6,6,6,6,6,6,6,6,6,6,6,6,6,6,6,6,6,6,6,6,6,6,6,6,6,6,6,6,6,6,6,6,6,6,6,6,6,6,6,6,6,6,6,6,6,6,6,6,6,6,6,6,6,6,6,6,6,6,6,6,6,6,6,6,6,6,6,6,6,6,6,6,6,6,6,6,6,6,6,6,6,6,6,6,6,6,6,6,6,6,6,6,6,6,6,6,6,6,6,6,6,6,6,6,6,6,6,6,6,6,6,6,6,6,6,6,6,6,6,6,6,6,6,6,6,6,6,6,6,6,6,6,6,6,6,6,6,6,6,6,6,6,6,6,6,6,6,6,6,6,6,6,6,6,6,6,6,6,6,6,6,6,6,6,6,6,6,6,6,6,6,6,6,6,6,6,6,6,6,6,6,6,6,6,6,6,6,6,6,6,6,7,7,7,7,7,7,7,7,7,7,7,7,7,8,8,8,8,8,8,8,8,8,8,8,9,10,10,10,10,10,10,10,10,10,10,10,10,10,10,10,10,10,10,10,10,10,10,10,10,10,10,10,10,10,10,10,10,10,10,10,10,10,10,10],"source":{"chars":{"starts":[4719,4719,4719,4719,4912,4934,5029,1306614,1306614,1306614,1306751,1306767,1757281,1757281,1757481,1763487,1763487,1763487,1763699,1763911,1764350,1764350,1764579,1764620,1764620,1764806,1766137,1766137,1766137,1766137,1766137,1766137,1766137,1766137,1766137,1766137,1766137,1766137,1766137,1766137,1766137,1766137,1766137,1766137,1766137,1766137,1766137,1766137,1766137,1766137,1766137,1766137,1766137,1766137,1766137,1766137,1766137,1766137,1766137,1766137,1766137,1766137,1766137,1766137,1766137,1766137,1766137,1766137,1766137,1766137,1766137,1766137,1766137,1766137,1766137,1766137,1766137,1766137,1766137,1766137,1766137,1766137,1766137,1766137,1766137,1766137,1766137,1766137,1766137,1766137,1766137,1766137,1766137,1766137,1766137,1766137,1766137,1766137,1766137,1766137,1766137,1766137,1766137,1766137,1766137,1766137,1766137,1766137,1766137,1766137,1766137,1766137,1766137,1766137,1766137,1766137,1766137,1766137,1766137,1766137,1766137,1766137,1766137,1766325,1766541,1766774,1766839,1766933,1767003,1767008,1767028,1767045,1767114,1767139,1767158,1767163,1767187,1767361,1767541,1767790,1768021,1768043,1768076,1768166,1768193,1768208,1768213,1768368,1768558,1768585,1768694,1768774,1768799,1768806,1768821,1768827,1768843,1768849,1768891,1768971,1768993,1769003,1769008,1769125,1769357,1769576,1769611,1769720,1769800,1769831,1769847,1769863,1769869,1769907,1769912,1769936,1769950,1769956,1769997,1770019,1770464,1770480,1770522,1770756,1770783,1770798,1770815,1770820,1770957,1771100,1771269,1771447,1771605,1771839,1771970,1772001,1772105,1772133,1772149,1772166,1772171,1772302,1772437,1772623,1772808,1772960,1772988,1773074,1773093,1773103,1773120,1773125,1773327,1773559,1773719,1773888,1774080,1774253,1774436,1774639,1775771,1775771,1775771,1775771,1775771,1775771,1775771,1775788,1775805,1775810,1775960,1776145,1776336,1855615,1855615,1855615,1855615,1855615,1855615,1855633,1855877,1855970,1855990,1856018,1856061,1856103,1856103,1856103,1856103,1856103,1856103,1856103,1856103,1856103,1856103,1856103,1856103,1856103,1856103,1856103,1856103,1856103,1856103,1856103,1856103,1856115,1856152,1856323,1856480,1856620,1856636,1856716,1856734,1856839,1856869,1856909,1856931,1857075,1857217,1857393,1857517,1857667,1857802,1858017],"lengths":[37,37,37,37,18,1,14,14,14,14,12,13,43,43,31,39,39,39,39,23,30,30,35,11,11,23,11,11,11,11,11,11,11,11,11,11,11,11,11,11,11,11,11,11,11,11,11,11,11,11,11,11,11,11,11,11,11,11,11,11,11,11,11,11,11,11,11,11,11,11,11,11,11,11,11,11,11,11,11,11,11,11,11,11,11,11,11,11,11,11,11,11,11,11,11,11,11,11,11,11,11,11,11,11,11,11,11,11,11,11,11,11,11,11,11,11,11,11,11,11,11,11,11,41,40,49,1,1,1,15,1,1,1,14,1,1,13,4,13,14,6,1,1,1,10,1,1,7,4,1,1,1,1,8,1,1,1,1,1,1,5,1,1,4,11,12,1,1,1,4,1,1,1,1,1,6,1,1,1,1,1,1,1,1,10,1,1,1,9,8,16,14,14,19,15,1,1,11,1,1,1,4,15,16,14,12,1,1,5,1,1,1,15,15,11,13,14,16,13,14,12,12,12,12,12,12,12,1,1,1,13,15,17,2,2,2,2,2,2,1,10,1,1,29,8,5,5,5,5,5,5,5,5,5,5,5,5,5,5,5,5,5,5,5,5,1,28,47,67,12,5,14,46,26,28,1,1,14,15,11,17,10,16,11]},"words":{"starts":[2,2,2,2,2,2,2,33466,33466,33466,33466,33466,40862,40862,40862,41029,41029,41029,41029,41029,41050,41050,41050,41059,41059,41059,41094,41094,41094,41094,41094,41094,41094,41094,41094,41094,41094,41094,41094,41094,41094,41094,41094,41094,41094,41094,41094,41094,41094,41094,41094,41094,41094,41094,41094,41094,41094,41094,41094,41094,41094,41094,41094,41094,41094,41094,41094,41094,41094,41094,41094,41094,41094,41094,41094,41094,41094,41094,41094,41094,41094,41094,41094,41094,41094,41094,41094,41094,41094,41094,41094,41094,41094,41094,41094,41094,41094,41094,41094,41094,41094,41094,41094,41094,41094,41094,41094,41094,41094,41094,41094,41094,41094,41094,41094,41094,41094,41094,41094,41094,41094,41094,41094,41094,41094,41094,41094,41094,41094,41094,41094,41094,41094,41094,41094,41094,41094,41094,41094,41094,41094,41094,41094,41094,41094,41094,41094,41094,41094,41094,41094,41094,41094,41094,41094,41094,41094,41094,41094,41094,41094,41094,41094,41094,41094,41094,41094,41094,41094,41094,41094,41094,41094,41094,41094,41094,41094,41094,41094,41094,41094,41094,41094,41094,41094,41094,41094,41094,41094,41094,41094,41094,41094,41094,41094,41094,41094,41094,41094,41094,41094,41094,41094,41094,41094,41094,41094,41094,41094,41094,41094,41094,41094,41094,41094,41094,41094,41094,41094,41094,41187,41187,41187,41187,41187,41187,41187,41187,41187,41187,41187,41187,41187,41550,41550,41550,41550,41550,41550,41550,41550,41550,41550,41550,41562,41565,41565,41565,41565,41565,41565,41565,41565,41565,41565,41565,41565,41565,41565,41565,41565,41565,41565,41565,41565,41565,41565,41565,41565,41565,41565,41565,41565,41565,41565,41565,41565,41565,41565,41565,41565,41565,41565,41565],"lengths":[10,10,10,10,10,10,10,6,6,6,6,6,7,7,7,12,12,12,12,12,7,7,7,3,3,3,84,84,84,84,84,84,84,84,84,84,84,84,84,84,84,84,84,84,84,84,84,84,84,84,84,84,84,84,84,84,84,84,84,84,84,84,84,84,84,84,84,84,84,84,84,84,84,84,84,84,84,84,84,84,84,84,84,84,84,84,84,84,84,84,84,84,84,84,84,84,84,84,84,84,84,84,84,84,84,84,84,84,84,84,84,84,84,84,84,84,84,84,84,84,84,84,84,84,84,84,84,84,84,84,84,84,84,84,84,84,84,84,84,84,84,84,84,84,84,84,84,84,84,84,84,84,84,84,84,84,84,84,84,84,84,84,84,84,84,84,84,84,84,84,84,84,84,84,84,84,84,84,84,84,84,84,84,84,84,84,84,84,84,84,84,84,84,84,84,84,84,84,84,84,84,84,84,84,84,84,84,84,84,84,84,84,84,84,84,84,84,84,84,84,8,8,8,8,8,8,8,8,8,8,8,8,8,9,9,9,9,9,9,9,9,9,9,9,1,52,52,52,52,52,52,52,52,52,52,52,52,52,52,52,52,52,52,52,52,52,52,52,52,52,52,52,52,52,52,52,52,52,52,52,52,52,52,52]}},"suspected":{"chars":{"starts":[3742,3953,3975,4088,3742,3742,3742,232996,233149,233165,232996,232996,445295,445495,445295,447466,447678,447892,447466,447466,448117,448336,448117,448372,448556,448372,448584,448772,448988,449221,449286,449372,449377,449397,449414,449483,449508,449527,449532,449556,449730,449910,450177,450426,450448,450481,450571,450598,450613,450618,450791,450999,451026,451135,451215,451240,451247,451262,451268,451284,451290,451332,451412,451434,451444,451449,451584,451834,452071,452106,452215,452295,452326,452342,452358,452364,452402,452407,452431,452445,452451,452492,452514,452959,452975,453017,453251,453278,453293,453310,453315,453452,453595,453764,453942,454100,454334,454465,454496,454600,454628,454644,454661,454666,454797,454932,455118,455303,455455,455483,455569,455588,455598,455615,455620,455840,456090,456250,456419,456629,456820,457007,457228,448584,448584,448584,448584,448584,448584,448584,448584,448584,448584,448584,448584,448584,448584,448584,448584,448584,448584,448584,448584,448584,448584,448584,448584,448584,448584,448584,448584,448584,448584,448584,448584,448584,448584,448584,448584,448584,448584,448584,448584,448584,448584,448584,448584,448584,448584,448584,448584,448584,448584,448584,448584,448584,448584,448584,448584,448584,448584,448584,448584,448584,448584,448584,448584,448584,448584,448584,448584,448584,448584,448584,448584,448584,448584,448584,448584,448584,448584,448584,448584,448584,448584,448584,448584,448584,448584,448584,448584,448584,448584,448584,448584,448584,448584,448584,448584,448584,457408,457425,457442,457447,457615,457825,458034,457408,457408,457408,457408,457408,457408,483302,483320,483568,483661,483681,483709,483302,483302,483302,483302,483302,483748,483790,483802,483839,484010,484167,484307,484323,484403,484421,484526,484556,484596,484618,484762,484904,485080,485204,485354,485489,485722,483790,483790,483790,483790,483790,483790,483790,483790,483790,483790,483790,483790,483790,483790,483790,483790,483790,483790,483790],"lengths":[37,18,1,14,37,37,37,14,12,13,14,14,43,31,43,39,39,23,39,39,30,35,30,11,23,11,11,41,40,49,1,1,15,1,1,1,14,1,1,13,4,13,14,6,1,1,1,10,1,1,7,4,1,1,1,1,8,1,1,1,1,1,1,5,1,1,4,11,12,1,1,1,4,1,1,1,1,1,6,1,1,1,1,1,1,1,1,10,1,1,1,9,8,16,14,14,19,15,1,1,11,1,1,1,4,15,16,14,12,1,1,5,1,1,1,15,15,11,13,14,16,13,14,11,11,11,11,11,11,11,11,11,11,11,11,11,11,11,11,11,11,11,11,11,11,11,11,11,11,11,11,11,11,11,11,11,11,11,11,11,11,11,11,11,11,11,11,11,11,11,11,11,11,11,11,11,11,11,11,11,11,11,11,11,11,11,11,11,11,11,11,11,11,11,11,11,11,11,11,11,11,11,11,11,11,11,11,11,11,11,11,11,11,11,11,11,11,11,11,11,12,1,1,1,13,15,17,12,12,12,12,12,12,2,1,10,1,1,29,2,2,2,2,2,8,5,1,28,47,67,12,5,14,46,26,28,1,1,14,15,11,17,10,16,11,5,5,5,5,5,5,5,5,5,5,5,5,5,5,5,5,5,5,5]},"words":{"starts":[3,3,3,3,3,3,3,9220,9220,9220,9220,9220,11736,11736,11736,11789,11789,11789,11789,11789,11805,11805,11805,11813,11813,11813,11818,11818,11818,11818,11818,11818,11818,11818,11818,11818,11818,11818,11818,11818,11818,11818,11818,11818,11818,11818,11818,11818,11818,11818,11818,11818,11818,11818,11818,11818,11818,11818,11818,11818,11818,11818,11818,11818,11818,11818,11818,11818,11818,11818,11818,11818,11818,11818,11818,11818,11818,11818,11818,11818,11818,11818,11818,11818,11818,11818,11818,11818,11818,11818,11818,11818,11818,11818,11818,11818,11818,11818,11818,11818,11818,11818,11818,11818,11818,11818,11818,11818,11818,11818,11818,11818,11818,11818,11818,11818,11818,11818,11818,11818,11818,11818,11818,11818,11818,11818,11818,11818,11818,11818,11818,11818,11818,11818,11818,11818,11818,11818,11818,11818,11818,11818,11818,11818,11818,11818,11818,11818,11818,11818,11818,11818,11818,11818,11818,11818,11818,11818,11818,11818,11818,11818,11818,11818,11818,11818,11818,11818,11818,11818,11818,11818,11818,11818,11818,11818,11818,11818,11818,11818,11818,11818,11818,11818,11818,11818,11818,11818,11818,11818,11818,11818,11818,11818,11818,11818,11818,11818,11818,11818,11818,11818,11818,11818,11818,11818,11818,11818,11818,11818,11818,11818,11818,11818,11818,11818,11818,11818,11818,11818,11903,11903,11903,11903,11903,11903,11903,11903,11903,11903,11903,11903,11903,12024,12024,12024,12024,12024,12024,12024,12024,12024,12024,12024,12036,12039,12039,12039,12039,12039,12039,12039,12039,12039,12039,12039,12039,12039,12039,12039,12039,12039,12039,12039,12039,12039,12039,12039,12039,12039,12039,12039,12039,12039,12039,12039,12039,12039,12039,12039,12039,12039,12039,12039],"lengths":[10,10,10,10,10,10,10,6,6,6,6,6,7,7,7,12,12,12,12,12,7,7,7,3,3,3,84,84,84,84,84,84,84,84,84,84,84,84,84,84,84,84,84,84,84,84,84,84,84,84,84,84,84,84,84,84,84,84,84,84,84,84,84,84,84,84,84,84,84,84,84,84,84,84,84,84,84,84,84,84,84,84,84,84,84,84,84,84,84,84,84,84,84,84,84,84,84,84,84,84,84,84,84,84,84,84,84,84,84,84,84,84,84,84,84,84,84,84,84,84,84,84,84,84,84,84,84,84,84,84,84,84,84,84,84,84,84,84,84,84,84,84,84,84,84,84,84,84,84,84,84,84,84,84,84,84,84,84,84,84,84,84,84,84,84,84,84,84,84,84,84,84,84,84,84,84,84,84,84,84,84,84,84,84,84,84,84,84,84,84,84,84,84,84,84,84,84,84,84,84,84,84,84,84,84,84,84,84,84,84,84,84,84,84,84,84,84,84,84,84,8,8,8,8,8,8,8,8,8,8,8,8,8,9,9,9,9,9,9,9,9,9,9,9,1,52,52,52,52,52,52,52,52,52,52,52,52,52,52,52,52,52,52,52,52,52,52,52,52,52,52,52,52,52,52,52,52,52,52,52,52,52,52,52]}}},"minorChanges":{"groupId":[11],"source":{"chars":{"starts":[1856048],"lengths":[2]},"words":{"starts":[41560],"lengths":[0]}},"suspected":{"chars":{"starts":[483739],"lengths":[2]},"words":{"starts":[12034],"lengths":[0]}}},"relatedMeaning":{"groupId":[12,13,14],"source":{"chars":{"starts":[1766130,1856051,1856070],"lengths":[6,9,5]},"words":{"starts":[41093,41561,41564],"lengths":[0,0,0]}},"suspected":{"chars":{"starts":[448580,483742,483757],"lengths":[3,5,5]},"words":{"starts":[11817,12035,12038],"lengths":[0,0,0]}}}}},"version":3}