{"Identical":[{"WC":2,"SoS":536,"SoE":549,"SoWS":68,"SoWE":69,"SuS":20183,"SuE":20196,"SuWS":3452,"SuWE":3453,"GID":0},{"WC":8,"SoS":550,"SoE":609,"SoWS":70,"SoWE":77,"SuS":20201,"SuE":20260,"SuWS":3455,"SuWE":3462,"GID":1},{"WC":11,"SoS":793,"SoE":858,"SoWS":105,"SoWE":115,"SuS":22003,"SuE":22068,"SuWS":3718,"SuWE":3728,"GID":9},{"WC":3,"SoS":865,"SoE":882,"SoWS":117,"SoWE":119,"SuS":22076,"SuE":22093,"SuWS":3730,"SuWE":3732,"GID":10},{"WC":9,"SoS":883,"SoE":944,"SoWS":120,"SoWE":128,"SuS":22099,"SuE":22160,"SuWS":3734,"SuWE":3742,"GID":11},{"WC":12,"SoS":2240,"SoE":2307,"SoWS":312,"SoWE":323,"SuS":21304,"SuE":21371,"SuWS":3612,"SuWE":3623,"GID":2},{"WC":1,"SoS":2485,"SoE":2487,"SoWS":350,"SoWE":350,"SuS":21541,"SuE":21543,"SuWS":3649,"SuWE":3649,"GID":3},{"WC":9,"SoS":2499,"SoE":2551,"SoWS":352,"SoWE":360,"SuS":21553,"SuE":21605,"SuWS":3652,"SuWE":3660,"GID":4},{"WC":4,"SoS":2595,"SoE":2621,"SoWS":368,"SoWE":371,"SuS":21640,"SuE":21666,"SuWS":3667,"SuWE":3670,"GID":5},{"WC":9,"SoS":2636,"SoE":2698,"SoWS":373,"SoWE":381,"SuS":21675,"SuE":21737,"SuWS":3672,"SuWE":3680,"GID":6},{"WC":3,"SoS":2708,"SoE":2729,"SoWS":383,"SoWE":385,"SuS":21748,"SuE":21769,"SuWS":3682,"SuWE":3684,"GID":7},{"WC":7,"SoS":2859,"SoE":2905,"SoWS":404,"SoWE":410,"SuS":21898,"SuE":21944,"SuWS":3703,"SuWE":3709,"GID":8},{"WC":9,"SoS":2997,"SoE":3057,"SoWS":423,"SoWE":431,"SuS":25030,"SuE":25090,"SuWS":4183,"SuWE":4191,"GID":12},{"WC":10,"SoS":3248,"SoE":3307,"SoWS":463,"SoWE":472,"SuS":25141,"SuE":25201,"SuWS":4201,"SuWE":4210,"GID":13},{"WC":16,"SoS":3321,"SoE":3408,"SoWS":474,"SoWE":489,"SuS":25209,"SuE":25296,"SuWS":4212,"SuWE":4227,"GID":14},{"WC":4,"SoS":3420,"SoE":3449,"SoWS":491,"SoWE":494,"SuS":25305,"SuE":25334,"SuWS":4229,"SuWE":4232,"GID":15},{"WC":9,"SoS":3609,"SoE":3657,"SoWS":516,"SoWE":524,"SuS":25457,"SuE":25505,"SuWS":4252,"SuWE":4260,"GID":16},{"WC":20,"SoS":3721,"SoE":3841,"SoWS":536,"SoWE":555,"SuS":25568,"SuE":25689,"SuWS":4272,"SuWE":4291,"GID":17},{"WC":14,"SoS":3977,"SoE":4065,"SoWS":574,"SoWE":587,"SuS":25701,"SuE":25790,"SuWS":4293,"SuWE":4306,"GID":18},{"WC":7,"SoS":4079,"SoE":4127,"SoWS":591,"SoWE":597,"SuS":25791,"SuE":25840,"SuWS":4307,"SuWE":4313,"GID":19},{"WC":10,"SoS":4153,"SoE":4222,"SoWS":601,"SoWE":610,"SuS":25892,"SuE":25962,"SuWS":4323,"SuWE":4332,"GID":20},{"WC":8,"SoS":4272,"SoE":4324,"SoWS":618,"SoWE":625,"SuS":25975,"SuE":26027,"SuWS":4334,"SuWE":4341,"GID":21},{"WC":2,"SoS":4331,"SoE":4344,"SoWS":627,"SoWE":628,"SuS":26028,"SuE":26041,"SuWS":4342,"SuWE":4343,"GID":22},{"WC":27,"SoS":4889,"SoE":5087,"SoWS":712,"SoWE":738,"SuS":26214,"SuE":26412,"SuWS":4369,"SuWE":4395,"GID":23},{"WC":24,"SoS":6059,"SoE":6244,"SoWS":872,"SoWE":895,"SuS":26413,"SuE":26600,"SuWS":4396,"SuWE":4419,"GID":24},{"WC":57,"SoS":6274,"SoE":6671,"SoWS":898,"SoWE":954,"SuS":26613,"SuE":27012,"SuWS":4421,"SuWE":4477,"GID":25},{"WC":22,"SoS":6912,"SoE":7068,"SoWS":984,"SoWE":1005,"SuS":27022,"SuE":27180,"SuWS":4479,"SuWE":4500,"GID":26},{"WC":14,"SoS":7088,"SoE":7198,"SoWS":1007,"SoWE":1020,"SuS":27192,"SuE":27303,"SuWS":4502,"SuWE":4515,"GID":27},{"WC":8,"SoS":7202,"SoE":7249,"SoWS":1022,"SoWE":1029,"SuS":27304,"SuE":27352,"SuWS":4516,"SuWE":4523,"GID":28},{"WC":17,"SoS":10686,"SoE":10781,"SoWS":1517,"SoWE":1533,"SuS":28044,"SuE":28141,"SuWS":4622,"SuWE":4638,"GID":30},{"WC":16,"SoS":11511,"SoE":11609,"SoWS":1642,"SoWE":1657,"SuS":28257,"SuE":28356,"SuWS":4657,"SuWE":4672,"GID":31},{"WC":42,"SoS":15472,"SoE":15768,"SoWS":2217,"SoWE":2258,"SuS":27412,"SuE":27712,"SuWS":4532,"SuWE":4573,"GID":29},{"WC":21,"SoS":15844,"SoE":15973,"SoWS":2265,"SoWE":2285,"SuS":31676,"SuE":31806,"SuWS":5174,"SuWE":5194,"GID":32},{"WC":3,"SoS":15974,"SoE":15993,"SoWS":2286,"SoWE":2288,"SuS":31816,"SuE":31835,"SuWS":5196,"SuWE":5198,"GID":33},{"WC":15,"SoS":16121,"SoE":16216,"SoWS":2307,"SoWE":2321,"SuS":31842,"SuE":31939,"SuWS":5200,"SuWE":5214,"GID":34},{"WC":12,"SoS":16248,"SoE":16318,"SoWS":2328,"SoWE":2339,"SuS":31982,"SuE":32053,"SuWS":5223,"SuWE":5234,"GID":35},{"WC":2,"SoS":16319,"SoE":16337,"SoWS":2340,"SoWE":2341,"SuS":32066,"SuE":32084,"SuWS":5236,"SuWE":5237,"GID":36},{"WC":1,"SoS":16338,"SoE":16348,"SoWS":2342,"SoWE":2342,"SuS":32090,"SuE":32100,"SuWS":5239,"SuWE":5239,"GID":37},{"WC":15,"SoS":16522,"SoE":16635,"SoWS":2370,"SoWE":2384,"SuS":32310,"SuE":32425,"SuWS":5275,"SuWE":5289,"GID":38},{"WC":11,"SoS":16665,"SoE":16741,"SoWS":2387,"SoWE":2397,"SuS":32438,"SuE":32515,"SuWS":5291,"SuWE":5301,"GID":39},{"WC":13,"SoS":16748,"SoE":16847,"SoWS":2399,"SoWE":2411,"SuS":32520,"SuE":32620,"SuWS":5303,"SuWE":5315,"GID":40},{"WC":11,"SoS":16869,"SoE":16952,"SoWS":2413,"SoWE":2423,"SuS":32634,"SuE":32717,"SuWS":5317,"SuWE":5327,"GID":41},{"WC":2,"SoS":16962,"SoE":16974,"SoWS":2425,"SoWE":2426,"SuS":32718,"SuE":32730,"SuWS":5328,"SuWE":5329,"GID":42},{"WC":4,"SoS":16975,"SoE":16992,"SoWS":2427,"SoWE":2430,"SuS":32740,"SuE":32757,"SuWS":5331,"SuWE":5334,"GID":43},{"WC":4,"SoS":17372,"SoE":17397,"SoWS":2479,"SoWE":2482,"SuS":33394,"SuE":33419,"SuWS":5434,"SuWE":5437,"GID":44},{"WC":16,"SoS":17407,"SoE":17518,"SoWS":2484,"SoWE":2499,"SuS":33425,"SuE":33536,"SuWS":5439,"SuWE":5454,"GID":45},{"WC":8,"SoS":17620,"SoE":17666,"SoWS":2514,"SoWE":2521,"SuS":33749,"SuE":33795,"SuWS":5484,"SuWE":5491,"GID":46},{"WC":33,"SoS":17941,"SoE":18153,"SoWS":2559,"SoWE":2591,"SuS":34068,"SuE":34283,"SuWS":5530,"SuWE":5562,"GID":47},{"WC":9,"SoS":18171,"SoE":18228,"SoWS":2593,"SoWE":2601,"SuS":34301,"SuE":34359,"SuWS":5564,"SuWE":5572,"GID":48},{"WC":61,"SoS":18255,"SoE":18718,"SoWS":2605,"SoWE":2665,"SuS":34387,"SuE":34856,"SuWS":5576,"SuWE":5636,"GID":49},{"WC":7,"SoS":18743,"SoE":18786,"SoWS":2669,"SoWE":2675,"SuS":34894,"SuE":34937,"SuWS":5642,"SuWE":5648,"GID":50},{"WC":11,"SoS":18792,"SoE":18881,"SoWS":2677,"SoWE":2687,"SuS":34944,"SuE":35033,"SuWS":5650,"SuWE":5660,"GID":51},{"WC":17,"SoS":18895,"SoE":19027,"SoWS":2689,"SoWE":2705,"SuS":35045,"SuE":35177,"SuWS":5662,"SuWE":5678,"GID":52},{"WC":8,"SoS":19049,"SoE":19102,"SoWS":2707,"SoWE":2714,"SuS":35196,"SuE":35249,"SuWS":5680,"SuWE":5687,"GID":53},{"WC":19,"SoS":19330,"SoE":19440,"SoWS":2746,"SoWE":2764,"SuS":35457,"SuE":35569,"SuWS":5716,"SuWE":5734,"GID":54},{"WC":7,"SoS":19555,"SoE":19608,"SoWS":2783,"SoWE":2789,"SuS":35680,"SuE":35733,"SuWS":5753,"SuWE":5759,"GID":55},{"WC":5,"SoS":19614,"SoE":19640,"SoWS":2791,"SoWE":2795,"SuS":35738,"SuE":35765,"SuWS":5761,"SuWE":5765,"GID":56},{"WC":6,"SoS":19646,"SoE":19680,"SoWS":2797,"SoWE":2802,"SuS":35772,"SuE":35806,"SuWS":5767,"SuWE":5772,"GID":57},{"WC":32,"SoS":19986,"SoE":20185,"SoWS":2845,"SoWE":2876,"SuS":36116,"SuE":36317,"SuWS":5816,"SuWE":5847,"GID":58},{"WC":14,"SoS":20191,"SoE":20291,"SoWS":2878,"SoWE":2891,"SuS":36325,"SuE":36425,"SuWS":5849,"SuWE":5862,"GID":59},{"WC":20,"SoS":20309,"SoE":20421,"SoWS":2895,"SoWE":2914,"SuS":36456,"SuE":36568,"SuWS":5869,"SuWE":5888,"GID":60},{"WC":21,"SoS":20430,"SoE":20555,"SoWS":2917,"SoWE":2937,"SuS":36586,"SuE":36712,"SuWS":5893,"SuWE":5913,"GID":61},{"WC":36,"SoS":20559,"SoE":20747,"SoWS":2939,"SoWE":2974,"SuS":36717,"SuE":36906,"SuWS":5915,"SuWE":5950,"GID":62},{"WC":18,"SoS":20769,"SoE":20912,"SoWS":2977,"SoWE":2994,"SuS":36928,"SuE":37073,"SuWS":5953,"SuWE":5970,"GID":63},{"WC":8,"SoS":21054,"SoE":21098,"SoWS":3020,"SoWE":3027,"SuS":37217,"SuE":37262,"SuWS":5996,"SuWE":6003,"GID":64},{"WC":3,"SoS":21220,"SoE":21235,"SoWS":3045,"SoWE":3047,"SuS":37386,"SuE":37401,"SuWS":6021,"SuWE":6023,"GID":65},{"WC":7,"SoS":21251,"SoE":21304,"SoWS":3049,"SoWE":3055,"SuS":37413,"SuE":37466,"SuWS":6025,"SuWE":6031,"GID":66},{"WC":1,"SoS":21326,"SoE":21329,"SoWS":3057,"SoWE":3057,"SuS":37485,"SuE":37488,"SuWS":6033,"SuWE":6033,"GID":67},{"WC":1,"SoS":21620,"SoE":21634,"SoWS":3101,"SoWE":3101,"SuS":38670,"SuE":38684,"SuWS":6207,"SuWE":6207,"GID":68},{"WC":29,"SoS":21654,"SoE":21863,"SoWS":3103,"SoWE":3131,"SuS":38699,"SuE":38910,"SuWS":6209,"SuWE":6237,"GID":69},{"WC":38,"SoS":21913,"SoE":22160,"SoWS":3138,"SoWE":3175,"SuS":38961,"SuE":39212,"SuWS":6244,"SuWE":6281,"GID":70},{"WC":2,"SoS":22184,"SoE":22192,"SoWS":3179,"SoWE":3180,"SuS":39236,"SuE":39244,"SuWS":6285,"SuWE":6286,"GID":71},{"WC":37,"SoS":22204,"SoE":22418,"SoWS":3182,"SoWE":3218,"SuS":39252,"SuE":39469,"SuWS":6288,"SuWE":6324,"GID":72},{"WC":3,"SoS":22592,"SoE":22606,"SoWS":3244,"SoWE":3246,"SuS":40604,"SuE":40618,"SuWS":6495,"SuWE":6497,"GID":73},{"WC":55,"SoS":22622,"SoE":23028,"SoWS":3249,"SoWE":3303,"SuS":40624,"SuE":41030,"SuWS":6499,"SuWE":6553,"GID":74},{"WC":16,"SoS":23065,"SoE":23183,"SoWS":3305,"SoWE":3320,"SuS":41044,"SuE":41162,"SuWS":6555,"SuWE":6570,"GID":75},{"WC":22,"SoS":23209,"SoE":23343,"SoWS":3322,"SoWE":3343,"SuS":41173,"SuE":41308,"SuWS":6572,"SuWE":6593,"GID":76},{"WC":3,"SoS":23669,"SoE":23690,"SoWS":3390,"SoWE":3392,"SuS":41639,"SuE":41660,"SuWS":6642,"SuWE":6644,"GID":77},{"WC":1,"SoS":23708,"SoE":23709,"SoWS":3394,"SoWE":3394,"SuS":41672,"SuE":41673,"SuWS":6646,"SuWE":6646,"GID":78},{"WC":6,"SoS":23710,"SoE":23752,"SoWS":3395,"SoWE":3400,"SuS":41681,"SuE":41723,"SuWS":6648,"SuWE":6653,"GID":79},{"WC":5,"SoS":23760,"SoE":23795,"SoWS":3402,"SoWE":3406,"SuS":41732,"SuE":41767,"SuWS":6655,"SuWE":6659,"GID":80},{"WC":54,"SoS":23812,"SoE":24134,"SoWS":3408,"SoWE":3461,"SuS":41780,"SuE":42106,"SuWS":6661,"SuWE":6714,"GID":81},{"WC":47,"SoS":24145,"SoE":24404,"SoWS":3463,"SoWE":3509,"SuS":42118,"SuE":42381,"SuWS":6716,"SuWE":6762,"GID":82},{"WC":9,"SoS":24462,"SoE":24519,"SoWS":3517,"SoWE":3525,"SuS":43352,"SuE":43409,"SuWS":6925,"SuWE":6933,"GID":83},{"WC":2,"SoS":24540,"SoE":24549,"SoWS":3527,"SoWE":3528,"SuS":43422,"SuE":43431,"SuWS":6935,"SuWE":6936,"GID":84},{"WC":58,"SoS":24554,"SoE":24923,"SoWS":3530,"SoWE":3587,"SuS":43435,"SuE":43807,"SuWS":6938,"SuWE":6995,"GID":85}],"Similar":[{"WC":1,"SoS":610,"SoE":617,"SoWS":78,"SoWE":78,"SuS":20261,"SuE":20268,"SuWS":3463,"SuWE":3463,"GID":0},{"WC":1,"SoS":859,"SoE":864,"SoWS":116,"SoWE":116,"SuS":22069,"SuE":22075,"SuWS":3729,"SuWE":3729,"GID":1},{"WC":1,"SoS":2552,"SoE":2558,"SoWS":361,"SoWE":361,"SuS":21606,"SuE":21613,"SuWS":3661,"SuWE":3661,"GID":2},{"WC":1,"SoS":2622,"SoE":2634,"SoWS":372,"SoWE":372,"SuS":21667,"SuE":21673,"SuWS":3671,"SuWE":3671,"GID":3},{"WC":1,"SoS":2699,"SoE":2707,"SoWS":382,"SoWE":382,"SuS":21738,"SuE":21747,"SuWS":3681,"SuWE":3681,"GID":4},{"WC":1,"SoS":2988,"SoE":2996,"SoWS":422,"SoWE":422,"SuS":25023,"SuE":25029,"SuWS":4182,"SuWE":4182,"GID":5},{"WC":1,"SoS":3062,"SoE":3069,"SoWS":433,"SoWE":433,"SuS":25100,"SuE":25103,"SuWS":4194,"SuWE":4194,"GID":6},{"WC":1,"SoS":3308,"SoE":3320,"SoWS":473,"SoWE":473,"SuS":25202,"SuE":25208,"SuWS":4211,"SuWE":4211,"GID":7},{"WC":1,"SoS":3409,"SoE":3419,"SoWS":490,"SoWE":490,"SuS":25297,"SuE":25304,"SuWS":4228,"SuWE":4228,"GID":8},{"WC":21,"SoS":3450,"SoE":3608,"SoWS":495,"SoWE":515,"SuS":25335,"SuE":25456,"SuWS":4233,"SuWE":4251,"GID":9},{"WC":1,"SoS":3842,"SoE":3851,"SoWS":556,"SoWE":556,"SuS":25691,"SuE":25700,"SuWS":4292,"SuWE":4292,"GID":10},{"WC":1,"SoS":4223,"SoE":4234,"SoWS":611,"SoWE":611,"SuS":25963,"SuE":25973,"SuWS":4333,"SuWE":4333,"GID":11},{"WC":1,"SoS":6245,"SoE":6264,"SoWS":896,"SoWE":896,"SuS":26601,"SuE":26612,"SuWS":4420,"SuWE":4420,"GID":12},{"WC":1,"SoS":6672,"SoE":6683,"SoWS":955,"SoWE":955,"SuS":27013,"SuE":27020,"SuWS":4478,"SuWE":4478,"GID":13},{"WC":1,"SoS":7069,"SoE":7087,"SoWS":1006,"SoWE":1006,"SuS":27181,"SuE":27191,"SuWS":4501,"SuWE":4501,"GID":14},{"WC":1,"SoS":7250,"SoE":7260,"SoWS":1030,"SoWE":1030,"SuS":27353,"SuE":27358,"SuWS":4524,"SuWE":4524,"GID":15},{"WC":1,"SoS":10782,"SoE":10793,"SoWS":1534,"SoWE":1534,"SuS":28142,"SuE":28152,"SuWS":4639,"SuWE":4639,"GID":16},{"WC":1,"SoS":11621,"SoE":11623,"SoWS":1659,"SoWE":1659,"SuS":28368,"SuE":28369,"SuWS":4674,"SuWE":4674,"GID":17},{"WC":1,"SoS":15769,"SoE":15786,"SoWS":2259,"SoWE":2259,"SuS":27714,"SuE":27727,"SuWS":4574,"SuWE":4574,"GID":18},{"WC":1,"SoS":15811,"SoE":15814,"SoWS":2261,"SoWE":2261,"SuS":27735,"SuE":27739,"SuWS":4576,"SuWE":4576,"GID":19},{"WC":1,"SoS":15994,"SoE":15998,"SoWS":2289,"SoWE":2289,"SuS":31836,"SuE":31841,"SuWS":5199,"SuWE":5199,"GID":20},{"WC":1,"SoS":16217,"SoE":16222,"SoWS":2322,"SoWE":2322,"SuS":31943,"SuE":31946,"SuWS":5216,"SuWE":5216,"GID":21},{"WC":1,"SoS":16848,"SoE":16868,"SoWS":2412,"SoWE":2412,"SuS":32621,"SuE":32633,"SuWS":5316,"SuWE":5316,"GID":22},{"WC":1,"SoS":16993,"SoE":17007,"SoWS":2431,"SoWE":2431,"SuS":32758,"SuE":32767,"SuWS":5335,"SuWE":5335,"GID":23},{"WC":1,"SoS":17398,"SoE":17406,"SoWS":2483,"SoWE":2483,"SuS":33420,"SuE":33424,"SuWS":5438,"SuWE":5438,"GID":24},{"WC":1,"SoS":18882,"SoE":18894,"SoWS":2688,"SoWE":2688,"SuS":35034,"SuE":35042,"SuWS":5661,"SuWE":5661,"GID":25},{"WC":1,"SoS":19028,"SoE":19048,"SoWS":2706,"SoWE":2706,"SuS":35178,"SuE":35194,"SuWS":5679,"SuWE":5679,"GID":26},{"WC":1,"SoS":19103,"SoE":19118,"SoWS":2715,"SoWE":2715,"SuS":35250,"SuE":35266,"SuWS":5688,"SuWE":5688,"GID":27},{"WC":1,"SoS":19965,"SoE":19985,"SoWS":2844,"SoWE":2844,"SuS":36099,"SuE":36115,"SuWS":5815,"SuWE":5815,"GID":28},{"WC":1,"SoS":21236,"SoE":21249,"SoWS":3048,"SoWE":3048,"SuS":37402,"SuE":37411,"SuWS":6024,"SuWE":6024,"GID":29},{"WC":1,"SoS":21305,"SoE":21325,"SoWS":3056,"SoWE":3056,"SuS":37468,"SuE":37484,"SuWS":6032,"SuWE":6032,"GID":30},{"WC":1,"SoS":21635,"SoE":21653,"SoWS":3102,"SoWE":3102,"SuS":38685,"SuE":38697,"SuWS":6208,"SuWE":6208,"GID":31},{"WC":1,"SoS":22193,"SoE":22203,"SoWS":3181,"SoWE":3181,"SuS":39245,"SuE":39251,"SuWS":6287,"SuWE":6287,"GID":32},{"WC":1,"SoS":23344,"SoE":23358,"SoWS":3344,"SoWE":3344,"SuS":41310,"SuE":41320,"SuWS":6594,"SuWE":6594,"GID":33},{"WC":1,"SoS":23691,"SoE":23707,"SoWS":3393,"SoWE":3393,"SuS":41661,"SuE":41671,"SuWS":6645,"SuWE":6645,"GID":34},{"WC":1,"SoS":23753,"SoE":23759,"SoWS":3401,"SoWE":3401,"SuS":41724,"SuE":41731,"SuWS":6654,"SuWE":6654,"GID":35},{"WC":1,"SoS":23796,"SoE":23811,"SoWS":3407,"SoWE":3407,"SuS":41768,"SuE":41779,"SuWS":6660,"SuWE":6660,"GID":36},{"WC":1,"SoS":24135,"SoE":24144,"SoWS":3462,"SoWE":3462,"SuS":42107,"SuE":42117,"SuWS":6715,"SuWE":6715,"GID":37},{"WC":1,"SoS":24405,"SoE":24414,"SoWS":3510,"SoWE":3510,"SuS":42382,"SuE":42387,"SuWS":6763,"SuWE":6763,"GID":38},{"WC":1,"SoS":24520,"SoE":24539,"SoWS":3526,"SoWE":3526,"SuS":43410,"SuE":43421,"SuWS":6934,"SuWE":6934,"GID":39}],"TotalWords":6562,"RelatedMeaning":[{"WC":1,"SoS":946,"SoE":956,"SoWS":129,"SoWE":129,"SuS":22161,"SuE":22169,"SuWS":3743,"SuWE":3743,"GID":0},{"WC":1,"SoS":960,"SoE":963,"SoWS":131,"SoWE":131,"SuS":22180,"SuE":22183,"SuWS":3745,"SuWE":3745,"GID":1},{"WC":1,"SoS":2488,"SoE":2498,"SoWS":351,"SoWE":351,"SuS":21548,"SuE":21552,"SuWS":3651,"SuWE":3651,"GID":2},{"WC":1,"SoS":2566,"SoE":2569,"SoWS":363,"SoWE":363,"SuS":21614,"SuE":21616,"SuWS":3662,"SuWE":3662,"GID":3},{"WC":1,"SoS":3058,"SoE":3061,"SoWS":432,"SoWE":432,"SuS":25095,"SuE":25099,"SuWS":4193,"SuWE":4193,"GID":4},{"WC":1,"SoS":4345,"SoE":4355,"SoWS":629,"SoWE":629,"SuS":26047,"SuE":26054,"SuWS":4345,"SuWE":4345,"GID":5},{"WC":1,"SoS":10794,"SoE":10797,"SoWS":1535,"SoWE":1535,"SuS":28164,"SuE":28166,"SuWS":4641,"SuWE":4641,"GID":6},{"WC":1,"SoS":10798,"SoE":10804,"SoWS":1536,"SoWE":1536,"SuS":28167,"SuE":28170,"SuWS":4642,"SuWE":4642,"GID":7},{"WC":1,"SoS":11610,"SoE":11620,"SoWS":1658,"SoWE":1658,"SuS":28357,"SuE":28367,"SuWS":4673,"SuWE":4673,"GID":8},{"WC":1,"SoS":15815,"SoE":15820,"SoWS":2262,"SoWE":2262,"SuS":27745,"SuE":27750,"SuWS":4578,"SuWE":4578,"GID":9},{"WC":1,"SoS":16351,"SoE":16358,"SoWS":2344,"SoWE":2344,"SuS":32104,"SuE":32106,"SuWS":5241,"SuWE":5241,"GID":10},{"WC":3,"SoS":18721,"SoE":18742,"SoWS":2666,"SoWE":2668,"SuS":34858,"SuE":34893,"SuWS":5637,"SuWE":5641,"GID":11},{"WC":1,"SoS":18787,"SoE":18791,"SoWS":2676,"SoWE":2676,"SuS":34938,"SuE":34943,"SuWS":5649,"SuWE":5649,"GID":12},{"WC":1,"SoS":19124,"SoE":19126,"SoWS":2717,"SoWE":2717,"SuS":35268,"SuE":35271,"SuWS":5689,"SuWE":5689,"GID":13},{"WC":1,"SoS":19641,"SoE":19645,"SoWS":2796,"SoWE":2796,"SuS":35766,"SuE":35771,"SuWS":5766,"SuWE":5766,"GID":14},{"WC":1,"SoS":20186,"SoE":20190,"SoWS":2877,"SoWE":2877,"SuS":36318,"SuE":36323,"SuWS":5848,"SuWE":5848,"GID":15},{"WC":1,"SoS":20297,"SoE":20299,"SoWS":2893,"SoWE":2893,"SuS":36432,"SuE":36434,"SuWS":5864,"SuWE":5864,"GID":16},{"WC":1,"SoS":20425,"SoE":20429,"SoWS":2916,"SoWE":2916,"SuS":36572,"SuE":36577,"SuWS":5890,"SuWE":5890,"GID":17},{"WC":1,"SoS":20556,"SoE":20558,"SoWS":2938,"SoWE":2938,"SuS":36713,"SuE":36716,"SuWS":5914,"SuWE":5914,"GID":18},{"WC":1,"SoS":22611,"SoE":22621,"SoWS":3248,"SoWE":3248,"SuS":40619,"SuE":40622,"SuWS":6498,"SuWE":6498,"GID":19},{"WC":1,"SoS":24550,"SoE":24553,"SoWS":3529,"SoWE":3529,"SuS":43432,"SuE":43434,"SuWS":6937,"SuWE":6937,"GID":20}],"IdenticalCopiedWords":1283,"SimilarCopiedWords":60,"RelatedMeaningCopiedWords":23,"TotalCopiedWords":1366}